{
  "refer": 1.15,
  "entry": 1.068,
  "register": 1.368,
  "members": 1.469,
  "financial": 1.068,
  "interests": 1.245,
  "former": 1.368,
  "colleagues": 1.395,
  "mcs": 11.279,
  "foundation": 1.299,
  "provided": 1.245,
  "research": 1.299,
  "support": 1.472,
  "bill": 1.487,
  "want": 1.457,
  "pick": 1.15,
  "hon": 1.486,
  "gentleman": 1.436,
  "point": 1.459,
  "timescales": 1.688,
  "experience": 1.299,
  "issue": 1.432,
  "one": 1.47,
  "raised": 1.376,
  "commonly": 1.664,
  "residents": 1.432,
  "wanting": 1.068,
  "see": 1.462,
  "action": 1.383,
  "earth": 1.068,
  "say": 1.443,
  "new": 1.481,
  "homes": 1.478,
  "put": 1.455,
  "without": 1.409,
  "solar": 0.0,
  "panels": 1.548,
  "time": 1.478,
  "essence": 0.693,
  "case": 1.42,
  "already": 1.454,
  "lost": 1.15,
  "many": 1.474,
  "opportunities": 1.347,
  "progress": 1.389,
  "regulations": 1.434,
  "due": 1.4,
  "come": 1.434,
  "force": 1.205,
  "would": 1.48,
  "required": 1.4,
  "zero": 1.441,
  "carbon": 1.425,
  "standards": 1.458,
  "scrapped": 0.322,
  "coalition": 0.935,
  "government": 1.484,
  "n": 1.275,
  "briefing": 0.054,
  "says": 1.245,
  "interruption": 1.068,
  "either": 0.935,
  "way": 1.46,
  "pleased": 1.376,
  "cross": 1.245,
  "party": 1.389,
  "today": 1.444,
  "press": 0.935,
  "ahead": 1.334,
  "proposal": 1.299,
  "speed": 1.318,
  "agree": 1.474,
  "ensure": 1.462,
  "thank": 1.462,
  "minister": 1.438,
  "generous": 1.068,
  "words": 1.068,
  "although": 1.376,
  "accept": 1.205,
  "cracking": 1.019,
  "open": 1.389,
  "beer": 2.556,
  "evening": 1.15,
  "celebrate": 1.275,
  "passing": 1.15,
  "perhaps": 1.334,
  "bottle": 2.541,
  "important": 1.472,
  "debate": 1.434,
  "demonstrated": 0.935,
  "consensus": 1.318,
  "across": 1.469,
  "house": 1.474,
  "save": 1.275,
  "local": 1.482,
  "difficulties": 1.068,
  "shadow": 1.245,
  "range": 1.15,
  "views": 1.275,
  "expressed": 1.15,
  "energy": 1.479,
  "mix": 1.275,
  "view": 1.275,
  "need": 1.476,
  "generation": 1.441,
  "includes": 1.205,
  "things": 1.389,
  "discussed": 1.245,
  "hear": 1.347,
  "matter": 1.275,
  "future": 1.464,
  "discussion": 1.299,
  "look": 1.432,
  "forward": 1.455,
  "working": 1.413,
  "particularly": 1.416,
  "applying": 1.347,
  "pressure": 1.376,
  "developers": 1.445,
  "gets": 1.205,
  "pragmatic": 0.312,
  "outcome": 0.935,
  "deserve": 1.068,
  "contributions": 1.299,
  "stood": 1.068,
  "adjourned": 0.935,
  "standing": 0.935,
  "order": 1.395,
  "ordered": 0.935,
  "resumed": 1.06,
  "wholeheartedly": 1.358,
  "incredibly": 1.15,
  "cool": 2.947,
  "alternatives": 0.264,
  "loud": 0.573,
  "fireworks": 6.032,
  "general": 1.441,
  "public": 1.449,
  "really": 1.409,
  "like": 1.441,
  "yougov": 4.118,
  "survey": 1.205,
  "recently": 1.299,
  "said": 1.445,
  "drones": 1.304,
  "popular": 1.068,
  "uk": 1.455,
  "seen": 1.358,
  "fantastic": 1.347,
  "drone": 1.64,
  "displays": 3.205,
  "also": 1.468,
  "low": 1.383,
  "noise": 1.029,
  "still": 1.4,
  "know": 1.465,
  "quite": 1.395,
  "buying": 1.245,
  "moment": 1.318,
  "hazard": 3.299,
  "guess": 0.835,
  "people": 1.482,
  "became": 1.15,
  "difference": 1.368,
  "firework": 7.328,
  "enable": 1.275,
  "encourage": 1.376,
  "educate": 0.797,
  "responsible": 1.205,
  "challenge": 1.318,
  "lobby": 1.068,
  "needs": 1.444,
  "diversify": 3.661,
  "hunger": 1.208,
  "among": 1.347,
  "consumers": 1.275,
  "quieter": 3.916,
  "increased": 1.275,
  "use": 1.459,
  "technology": 1.422,
  "change": 1.455,
  "behind": 1.299,
  "us": 1.459,
  "deputy": 1.318,
  "speaker": 1.245,
  "interrupted": 1.455,
  "business": 1.299,
  "first": 1.453,
  "chairman": 0.68,
  "ways": 1.347,
  "means": 1.389,
  "took": 1.205,
  "chair": 0.68,
  "beg": 1.205,
  "move": 1.395,
  "sit": 1.068,
  "private": 1.334,
  "question": 1.334,
  "forthwith": 0.68,
  "second": 1.464,
  "reading": 1.383,
  "read": 1.454,
  "sunshine": 4.337,
  "heart": 1.358,
  "environmentalist": 4.9,
  "fought": 0.68,
  "years": 1.455,
  "improve": 1.275,
  "housing": 1.469,
  "market": 1.245,
  "town": 1.299,
  "cheltenham": 4.397,
  "strongly": 1.068,
  "believe": 1.416,
  "fairer": 0.68,
  "deal": 1.275,
  "cost": 1.436,
  "living": 1.383,
  "elected": 1.275,
  "july": 1.245,
  "campaigning": 1.068,
  "three": 1.358,
  "issues": 1.383,
  "mind": 1.15,
  "taken": 1.299,
  "attend": 0.935,
  "urge": 1.205,
  "retain": 0.68,
  "sunny": 4.179,
  "disposition": 4.366,
  "next": 1.425,
  "hours": 1.434,
  "happy": 1.245,
  "take": 1.449,
  "interventions": 1.068,
  "hope": 1.445,
  "throw": 0.014,
  "much": 1.458,
  "shade": 3.533,
  "promise": 0.935,
  "warm": 1.245,
  "response": 1.245,
  "regardless": 0.68,
  "provide": 1.42,
  "make": 1.473,
  "commitment": 1.358,
  "brighter": 0.712,
  "backing": 0.68,
  "lower": 1.358,
  "household": 1.068,
  "bills": 1.434,
  "less": 1.358,
  "reliant": 0.68,
  "dirty": 1.073,
  "expensive": 1.15,
  "fossil": 0.726,
  "fuels": 0.457,
  "often": 1.4,
  "imported": 0.837,
  "abroad": 0.68,
  "country": 1.462,
  "supplies": 0.68,
  "secure": 1.358,
  "vision": 0.68,
  "supported": 1.205,
  "voters": 1.463,
  "political": 1.368,
  "divides": 1.619,
  "well": 1.441,
  "industry": 1.44,
  "get": 1.452,
  "core": 1.15,
  "speech": 1.334,
  "ask": 1.334,
  "think": 1.43,
  "back": 1.425,
  "short": 1.299,
  "start": 1.376,
  "crisis": 1.425,
  "householders": 4.585,
  "endured": 0.621,
  "rise": 1.15,
  "price": 1.299,
  "cap": 0.935,
  "april": 0.68,
  "remain": 1.358,
  "higher": 1.334,
  "caused": 1.068,
  "widespread": 1.205,
  "fuel": 1.15,
  "poverty": 0.935,
  "witnessed": 0.935,
  "another": 1.405,
  "shocking": 0.935,
  "increase": 1.376,
  "food": 1.347,
  "bank": 0.68,
  "businesses": 1.409,
  "went": 1.15,
  "bust": 1.395,
  "jobs": 1.275,
  "family": 1.245,
  "holiday": 1.205,
  "plans": 1.389,
  "cancelled": 0.935,
  "laid": 0.935,
  "bare": 0.452,
  "sighted": 1.331,
  "past": 1.405,
  "ideological": 0.231,
  "decisions": 1.205,
  "slow": 0.68,
  "roll": 0.935,
  "renewable": 1.405,
  "technologies": 1.245,
  "imagine": 1.205,
  "alternative": 1.245,
  "included": 1.334,
  "power": 1.452,
  "ongoing": 1.205,
  "could": 1.458,
  "hundreds": 1.15,
  "pounds": 0.68,
  "everyone": 1.368,
  "insulated": 2.003,
  "nation": 1.068,
  "safer": 0.68,
  "stronger": 1.068,
  "banks": 0.68,
  "busy": 0.68,
  "forced": 0.935,
  "give": 1.425,
  "large": 1.395,
  "subsidies": 1.64,
  "pressing": 1.068,
  "tackle": 1.334,
  "twin": 1.663,
  "crises": 0.275,
  "climate": 1.452,
  "leads": 0.68,
  "difficult": 1.4,
  "trade": 0.68,
  "offs": 1.32,
  "grappling": 2.285,
  "good": 1.43,
  "wishes": 1.15,
  "build": 1.447,
  "category": 0.0,
  "helps": 1.15,
  "clear": 1.443,
  "win": 1.299,
  "shown": 0.935,
  "payback": 4.054,
  "period": 1.334,
  "array": 2.348,
  "bedroom": 1.556,
  "semi": 2.359,
  "detached": 2.548,
  "four": 1.275,
  "combined": 1.205,
  "widely": 1.068,
  "available": 1.413,
  "year": 1.461,
  "mortgage": 0.234,
  "savings": 1.068,
  "stand": 1.299,
  "whopping": 1.849,
  "offers": 1.068,
  "homeowners": 1.827,
  "chance": 1.275,
  "profit": 1.245,
  "directly": 1.15,
  "saving": 1.068,
  "trust": 1.318,
  "estimates": 1.068,
  "typical": 0.068,
  "environmental": 1.389,
  "side": 1.245,
  "shows": 1.15,
  "buildings": 1.445,
  "accounted": 1.395,
  "emissions": 1.358,
  "placed": 1.205,
  "building": 1.458,
  "agenda": 1.275,
  "genuinely": 0.935,
  "welcome": 1.425,
  "brought": 1.368,
  "two": 1.42,
  "parliament": 1.451,
  "benches": 1.15,
  "wish": 1.347,
  "every": 1.441,
  "success": 1.15,
  "long": 1.389,
  "journey": 1.205,
  "impact": 1.395,
  "environment": 1.409,
  "green": 1.469,
  "belt": 0.82,
  "shift": 0.935,
  "towards": 1.347,
  "using": 1.245,
  "fear": 1.205,
  "installed": 2.037,
  "prime": 1.068,
  "agricultural": 1.299,
  "land": 1.456,
  "disappointed": 0.68,
  "walsall": 2.115,
  "planning": 1.451,
  "inspector": 1.356,
  "given": 1.368,
  "permission": 1.15,
  "battery": 1.331,
  "storage": 0.149,
  "facility": 0.68,
  "edge": 0.935,
  "constituency": 1.465,
  "right": 1.47,
  "conservation": 1.987,
  "area": 1.443,
  "feel": 1.347,
  "places": 1.275,
  "protect": 1.334,
  "communities": 1.451,
  "lady": 1.334,
  "entirely": 1.299,
  "noted": 1.15,
  "campaign": 1.15,
  "rural": 1.245,
  "england": 1.44,
  "strong": 1.347,
  "interest": 1.299,
  "precisely": 0.935,
  "reasons": 1.347,
  "describes": 0.68,
  "lot": 1.395,
  "sympathy": 0.68,
  "efficient": 1.334,
  "space": 1.395,
  "extremely": 1.068,
  "achieve": 1.334,
  "home": 1.44,
  "targets": 1.413,
  "set": 1.438,
  "must": 1.463,
  "equipped": 0.575,
  "challenges": 1.334,
  "include": 0.935,
  "looking": 1.334,
  "stock": 1.245,
  "miss": 0.68,
  "economic": 1.245,
  "opportunity": 1.443,
  "risk": 1.275,
  "advisory": 0.68,
  "body": 0.68,
  "committee": 1.395,
  "advised": 0.935,
  "meet": 1.409,
  "near": 1.15,
  "complete": 1.15,
  "decarbonisation": 0.623,
  "specifically": 1.15,
  "secretary": 1.383,
  "state": 1.383,
  "moved": 1.15,
  "conversation": 1.15,
  "along": 1.299,
  "least": 1.299,
  "answer": 1.205,
  "asked": 1.334,
  "christmas": 0.935,
  "sympathetic": 1.102,
  "mandatory": 1.358,
  "updating": 0.167,
  "irrefutable": 3.807,
  "govern": 0.396,
  "work": 1.465,
  "act": 1.413,
  "born": 0.68,
  "ago": 1.318,
  "disturbed": 1.899,
  "learn": 0.935,
  "days": 1.245,
  "previous": 1.425,
  "consulted": 1.245,
  "standard": 1.395,
  "able": 1.425,
  "respond": 1.299,
  "election": 1.466,
  "heartening": 2.174,
  "current": 1.318,
  "promised": 1.068,
  "course": 1.395,
  "pushback": 4.642,
  "default": 0.718,
  "thinking": 1.068,
  "understand": 1.389,
  "motive": 2.548,
  "planet": 0.051,
  "customers": 1.068,
  "demanding": 0.162,
  "member": 1.465,
  "puns": 5.077,
  "making": 1.447,
  "completely": 1.275,
  "utterly": 0.68,
  "ancient": 0.833,
  "setting": 1.299,
  "aside": 1.068,
  "serious": 1.15,
  "supply": 1.358,
  "chain": 0.935,
  "eliminate": 0.653,
  "built": 1.438,
  "uyghur": 2.267,
  "subject": 1.318,
  "labour": 1.42,
  "china": 0.935,
  "makes": 1.409,
  "reasonable": 1.068,
  "chains": 1.245,
  "free": 1.205,
  "slave": 1.825,
  "procurement": 0.68,
  "rules": 1.299,
  "measures": 1.405,
  "saying": 1.347,
  "motives": 2.436,
  "push": 1.205,
  "exists": 0.935,
  "implementing": 1.15,
  "relatively": 1.15,
  "straightforward": 1.245,
  "panel": 1.299,
  "construction": 1.318,
  "accustomed": 3.059,
  "mandating": 1.801,
  "installation": 1.93,
  "stage": 1.275,
  "logical": 2.043,
  "removes": 0.897,
  "burden": 1.245,
  "responsibility": 1.299,
  "developer": 1.844,
  "friend": 1.48,
  "bringing": 1.376,
  "almost": 1.368,
  "feels": 0.68,
  "brainer": 3.668,
  "share": 1.347,
  "frustration": 1.068,
  "trying": 1.15,
  "navigate": 0.279,
  "process": 1.46,
  "installing": 3.472,
  "questions": 1.205,
  "provider": 0.68,
  "go": 1.45,
  "works": 1.068,
  "technical": 1.334,
  "details": 1.205,
  "benefit": 1.413,
  "started": 1.275,
  "explain": 1.068,
  "empower": 0.68,
  "knows": 1.299,
  "recommendation": 0.935,
  "confidence": 1.205,
  "removed": 0.68,
  "creates": 1.205,
  "efficiency": 1.395,
  "human": 0.68,
  "resources": 1.068,
  "materials": 0.935,
  "step": 1.368,
  "roofs": 3.503,
  "houses": 1.42,
  "cheaper": 1.15,
  "retrofitting": 4.852,
  "around": 1.413,
  "might": 1.368,
  "raise": 1.15,
  "speeches": 0.935,
  "per": 1.205,
  "sounds": 0.68,
  "money": 1.318,
  "isolation": 1.068,
  "average": 1.205,
  "final": 1.405,
  "quarter": 0.68,
  "far": 1.368,
  "excess": 0.127,
  "talking": 1.299,
  "little": 1.334,
  "nothing": 1.068,
  "context": 1.299,
  "monthly": 0.682,
  "repayment": 1.849,
  "figure": 1.068,
  "raw": 0.848,
  "form": 1.405,
  "offset": 1.357,
  "mandate": 1.15,
  "covering": 1.15,
  "roof": 1.413,
  "minimum": 0.68,
  "equivalent": 1.205,
  "ground": 1.368,
  "floor": 1.205,
  "interested": 1.15,
  "mandated": 1.454,
  "school": 1.358,
  "retrofitted": 6.268,
  "educational": 1.15,
  "facilities": 0.935,
  "effects": 0.935,
  "teach": 0.787,
  "young": 1.422,
  "nhs": 0.935,
  "south": 1.383,
  "facing": 1.205,
  "hospitals": 1.068,
  "wonder": 0.68,
  "extend": 1.318,
  "board": 1.205,
  "limited": 1.299,
  "residential": 1.15,
  "builds": 1.383,
  "conscious": 0.935,
  "sector": 1.4,
  "initial": 0.935,
  "borne": 0.58,
  "taxpayer": 0.68,
  "reference": 1.068,
  "schools": 1.358,
  "huge": 1.347,
  "source": 1.068,
  "heat": 1.334,
  "pump": 1.839,
  "national": 1.456,
  "leading": 1.15,
  "study": 1.068,
  "going": 1.405,
  "regard": 0.935,
  "sure": 1.444,
  "wide": 0.935,
  "regulator": 0.68,
  "certification": 2.174,
  "scheme": 1.068,
  "proper": 0.68,
  "regulation": 1.205,
  "product": 0.68,
  "mentioned": 1.368,
  "adjust": 1.211,
  "proposes": 0.137,
  "apply": 1.447,
  "exemptions": 0.944,
  "including": 1.422,
  "tall": 2.115,
  "economical": 3.533,
  "install": 2.689,
  "size": 1.15,
  "factors": 1.245,
  "forms": 1.15,
  "appropriate": 1.368,
  "physically": 0.513,
  "accommodate": 0.669,
  "cover": 1.318,
  "requires": 1.068,
  "maximum": 1.15,
  "extent": 1.068,
  "possible": 1.441,
  "part": 1.453,
  "myth": 2.79,
  "busting": 1.849,
  "dispel": 4.203,
  "big": 1.299,
  "always": 1.358,
  "day": 1.383,
  "continue": 1.358,
  "conditions": 1.15,
  "news": 1.068,
  "effect": 1.15,
  "north": 1.434,
  "overwhelming": 1.068,
  "strength": 1.068,
  "measure": 1.347,
  "gathered": 0.978,
  "several": 1.275,
  "organisations": 1.15,
  "signed": 1.15,
  "letter": 0.68,
  "declared": 0.68,
  "grateful": 1.299,
  "assistance": 0.935,
  "advice": 0.935,
  "matters": 1.275,
  "last": 1.436,
  "months": 1.275,
  "letting": 1.068,
  "interrupt": 1.825,
  "excellent": 1.15,
  "loaded": 2.174,
  "proud": 1.4,
  "discussions": 1.245,
  "correct": 1.334,
  "skills": 1.347,
  "pipeline": 0.223,
  "enough": 1.376,
  "installers": 3.709,
  "efficiently": 0.66,
  "effectively": 0.68,
  "maximise": 0.935,
  "absolutely": 1.436,
  "recall": 0.68,
  "decade": 0.935,
  "thriving": 0.935,
  "sadly": 1.205,
  "steps": 0.935,
  "comes": 1.368,
  "date": 1.358,
  "education": 1.358,
  "colleges": 0.203,
  "courses": 0.299,
  "train": 0.935,
  "excludes": 1.754,
  "thermal": 4.283,
  "focuses": 1.068,
  "different": 1.42,
  "type": 0.935,
  "covered": 1.15,
  "cpre": 6.533,
  "becoming": 0.935,
  "increasingly": 1.245,
  "worrying": 0.935,
  "starting": 0.935,
  "policy": 1.413,
  "grey": 2.109,
  "thoroughly": 0.191,
  "grasp": 0.336,
  "renewables": 0.341,
  "infrastructure": 1.416,
  "sudden": 0.609,
  "speaks": 1.205,
  "powerfully": 0.068,
  "specific": 1.205,
  "head": 1.205,
  "parapet": 4.668,
  "applauded": 2.757,
  "supporting": 1.376,
  "sound": 1.068,
  "preference": 1.891,
  "small": 1.4,
  "proportion": 1.068,
  "rewarded": 1.259,
  "decent": 0.68,
  "politically": 0.186,
  "demonstrable": 3.308,
  "found": 1.347,
  "supportive": 1.205,
  "suspect": 0.935,
  "percentage": 0.935,
  "barometer": 3.453,
  "tracks": 1.283,
  "majority": 1.245,
  "parties": 1.205,
  "place": 1.444,
  "centre": 1.299,
  "gravity": 1.32,
  "conservative": 1.358,
  "liberal": 1.318,
  "democrat": 1.245,
  "reform": 1.299,
  "supporters": 0.127,
  "responded": 0.935,
  "favour": 1.068,
  "constituents": 1.428,
  "rightly": 1.245,
  "evidence": 0.935,
  "points": 1.334,
  "benefits": 1.358,
  "level": 1.368,
  "positive": 1.245,
  "million": 1.389,
  "additional": 1.368,
  "sizewell": 2.575,
  "c": 1.068,
  "nuclear": 1.068,
  "stations": 1.245,
  "pause": 0.68,
  "thought": 1.299,
  "struggles": 0.466,
  "easier": 1.44,
  "scale": 1.299,
  "wins": 1.04,
  "congratulate": 1.405,
  "introducing": 1.245,
  "talks": 1.245,
  "may": 1.444,
  "needed": 1.376,
  "demand": 1.15,
  "farms": 1.383,
  "concerns": 1.405,
  "suspicion": 1.107,
  "help": 1.436,
  "decide": 1.068,
  "inevitable": 0.935,
  "produce": 1.068,
  "sources": 1.15,
  "areas": 1.395,
  "visited": 1.299,
  "hinkley": 4.328,
  "trip": 0.176,
  "old": 1.275,
  "told": 1.299,
  "regret": 0.68,
  "tell": 1.245,
  "projections": 1.663,
  "expected": 1.068,
  "generate": 1.318,
  "outlast": 4.474,
  "better": 1.416,
  "lasting": 1.068,
  "testament": 0.68,
  "efforts": 1.068,
  "offer": 0.935,
  "protections": 1.15,
  "shocks": 1.057,
  "ministers": 1.318,
  "willing": 0.935,
  "principles": 1.068,
  "let": 1.4,
  "pass": 1.245,
  "duty": 1.245,
  "match": 1.15,
  "paraphrase": 3.004,
  "great": 1.449,
  "morecambe": 1.874,
  "wise": 0.68,
  "song": 1.619,
  "shares": 0.68,
  "informal": 1.801,
  "name": 1.15,
  "arms": 1.205,
  "sun": 1.607,
  "joy": 0.935,
  "brand": 0.081,
  "bright": 0.111,
  "tomorrow": 1.15,
  "glad": 1.068,
  "whole": 1.383,
  "embrace": 1.13,
  "live": 1.347,
  "frequently": 0.935,
  "comment": 1.205,
  "facebook": 1.338,
  "lived": 1.15,
  "adult": 0.935,
  "life": 1.376,
  "tower": 1.211,
  "blocks": 1.048,
  "council": 1.449,
  "everybody": 1.205,
  "decades": 0.935,
  "apparent": 0.935,
  "missing": 1.068,
  "acreage": 4.9,
  "rooftops": 5.181,
  "empty": 0.68,
  "devoid": 3.004,
  "countries": 1.205,
  "leapt": 4.032,
  "advantage": 1.245,
  "worked": 1.245,
  "watched": 0.081,
  "block": 1.15,
  "saw": 1.245,
  "problems": 1.334,
  "management": 0.935,
  "company": 0.935,
  "unused": 3.072,
  "functioning": 0.68,
  "sign": 1.205,
  "mature": 1.474,
  "five": 1.299,
  "happened": 0.935,
  "constituencies": 1.358,
  "lots": 1.15,
  "conversations": 1.318,
  "pubs": 0.492,
  "talk": 1.358,
  "length": 0.68,
  "reduced": 0.68,
  "unfortunately": 1.068,
  "others": 1.299,
  "getting": 1.334,
  "connected": 0.68,
  "grid": 0.386,
  "reason": 1.347,
  "eye": 0.935,
  "hopefully": 1.15,
  "successful": 0.935,
  "loads": 1.535,
  "lose": 0.935,
  "sight": 1.15,
  "impressive": 0.285,
  "industrial": 1.068,
  "cluster": 1.544,
  "factories": 1.755,
  "paper": 1.389,
  "mill": 1.818,
  "ds": 4.308,
  "smith": 0.68,
  "third": 1.275,
  "produced": 1.15,
  "recycled": 2.987,
  "location": 0.935,
  "waste": 1.15,
  "products": 1.068,
  "circular": 3.021,
  "economy": 1.299,
  "key": 1.245,
  "traditional": 1.15,
  "production": 1.299,
  "instance": 1.068,
  "used": 1.422,
  "turned": 0.935,
  "electricity": 1.376,
  "capture": 0.935,
  "expand": 1.205,
  "landfill": 1.849,
  "site": 1.068,
  "perfectly": 1.245,
  "factory": 0.368,
  "suitable": 1.245,
  "locally": 1.15,
  "play": 1.368,
  "close": 1.275,
  "eyes": 0.68,
  "fact": 1.376,
  "ensuring": 1.443,
  "reach": 1.245,
  "fixing": 0.935,
  "mutually": 1.514,
  "exclusive": 1.925,
  "identified": 1.068,
  "add": 1.358,
  "disagree": 0.68,
  "made": 1.464,
  "times": 1.368,
  "tension": 1.247,
  "protecting": 1.15,
  "natural": 1.068,
  "choice": 1.334,
  "central": 1.205,
  "councillor": 1.205,
  "vital": 1.425,
  "community": 1.389,
  "voices": 1.205,
  "heard": 1.405,
  "thing": 1.334,
  "upsets": 3.709,
  "involved": 1.205,
  "gave": 0.935,
  "example": 1.368,
  "generator": 3.177,
  "came": 1.275,
  "causing": 1.068,
  "leaks": 1.663,
  "sorts": 0.68,
  "stuff": 0.68,
  "monetary": 0.757,
  "pockets": 1.068,
  "lights": 0.738,
  "heating": 0.322,
  "keen": 0.935,
  "plan": 1.452,
  "aspirations": 0.582,
  "comprehensive": 1.205,
  "strategy": 1.15,
  "net": 1.416,
  "tackling": 1.205,
  "biodiversity": 1.102,
  "joined": 0.935,
  "deliver": 1.389,
  "happens": 1.205,
  "implementation": 1.245,
  "tricky": 2.031,
  "intention": 1.275,
  "full": 1.318,
  "intentions": 0.0,
  "hot": 0.231,
  "cold": 1.205,
  "sometimes": 1.205,
  "hell": 1.193,
  "leather": 3.378,
  "seem": 0.935,
  "certain": 1.15,
  "households": 1.205,
  "struggled": 0.122,
  "direction": 1.15,
  "travel": 0.935,
  "hopeful": 0.699,
  "focus": 0.935,
  "stability": 1.068,
  "plank": 2.366,
  "growth": 1.318,
  "giving": 1.347,
  "certainty": 0.68,
  "together": 1.405,
  "framework": 1.383,
  "towns": 1.275,
  "face": 1.405,
  "greater": 1.383,
  "sheerness": 4.668,
  "deteriorating": 1.825,
  "quality": 1.358,
  "post": 1.432,
  "war": 0.68,
  "unsurprisingly": 1.598,
  "coastal": 0.68,
  "high": 1.425,
  "maintenance": 1.068,
  "costs": 1.413,
  "renewal": 0.935,
  "brings": 1.15,
  "leapfrog": 4.668,
  "stages": 0.935,
  "learning": 1.068,
  "ensures": 1.068,
  "speaking": 1.068,
  "passion": 0.935,
  "consider": 1.347,
  "top": 1.245,
  "bottom": 0.68,
  "cheap": 0.064,
  "scotland": 1.461,
  "introduced": 1.334,
  "alex": 0.272,
  "rowley": 2.712,
  "msp": 3.661,
  "mean": 1.358,
  "gold": 0.313,
  "aspire": 1.454,
  "coming": 1.318,
  "generally": 1.275,
  "damp": 1.43,
  "parts": 1.334,
  "pretty": 1.068,
  "wind": 1.245,
  "swale": 5.19,
  "kent": 0.091,
  "insulation": 1.384,
  "attention": 1.15,
  "picture": 0.935,
  "ultimately": 1.15,
  "felt": 0.935,
  "expertise": 1.15,
  "depth": 0.68,
  "happening": 1.15,
  "listening": 0.935,
  "mistakes": 0.935,
  "practice": 0.935,
  "policies": 1.068,
  "actually": 1.205,
  "unlike": 0.68,
  "false": 0.68,
  "starts": 0.68,
  "east": 1.376,
  "losing": 0.935,
  "grade": 0.956,
  "development": 1.447,
  "unnecessary": 1.245,
  "outside": 1.245,
  "acres": 2.653,
  "ownership": 0.68,
  "prisons": 0.244,
  "addition": 0.68,
  "car": 0.935,
  "park": 1.068,
  "french": 0.68,
  "whatsoever": 1.068,
  "purposes": 0.935,
  "fine": 1.068,
  "growing": 1.275,
  "crops": 1.754,
  "feeding": 1.04,
  "scope": 1.068,
  "though": 0.68,
  "done": 1.395,
  "water": 1.275,
  "systems": 1.409,
  "gallons": 6.148,
  "soak": 3.709,
  "tarmac": 3.453,
  "replenishing": 4.308,
  "aquifers": 4.308,
  "ought": 0.935,
  "flushing": 4.668,
  "require": 1.376,
  "trick": 1.685,
  "missed": 1.15,
  "clearly": 1.275,
  "happen": 1.245,
  "builders": 2.145,
  "scream": 4.162,
  "stuck": 1.068,
  "pigs": 2.757,
  "herne": 4.032,
  "bay": 1.094,
  "hate": 0.935,
  "upset": 0.927,
  "taylor": 0.864,
  "wimpey": 4.162,
  "avoided": 0.978,
  "electric": 0.935,
  "vehicle": 0.68,
  "charging": 0.68,
  "bit": 1.275,
  "wriggle": 4.971,
  "room": 1.068,
  "amount": 1.245,
  "property": 1.275,
  "allows": 1.245,
  "hook": 1.434,
  "doubt": 1.15,
  "initially": 0.935,
  "purchase": 1.15,
  "eat": 0.258,
  "essential": 1.368,
  "notice": 1.299,
  "gives": 1.068,
  "immediately": 0.935,
  "fitted": 3.145,
  "photovoltaic": 6.622,
  "design": 1.245,
  "unattractive": 4.032,
  "hideous": 3.251,
  "blunt": 1.598,
  "surprises": 2.757,
  "age": 1.205,
  "developing": 1.15,
  "gone": 1.299,
  "fast": 1.068,
  "develop": 1.245,
  "attractive": 0.162,
  "simply": 1.376,
  "got": 1.299,
  "tile": 6.733,
  "listed": 1.245,
  "advise": 0.68,
  "referencing": 2.267,
  "acceptable": 1.15,
  "enforcing": 1.193,
  "relating": 0.935,
  "delighted": 1.334,
  "wonderful": 1.205,
  "county": 1.15,
  "ii": 0.566,
  "present": 1.275,
  "permitted": 0.53,
  "tiles": 3.709,
  "even": 1.405,
  "cottages": 4.162,
  "whatever": 1.15,
  "within": 1.347,
  "considerable": 1.245,
  "quantity": 2.138,
  "king": 1.068,
  "college": 0.68,
  "cambridge": 0.537,
  "oldest": 0.699,
  "prestigious": 2.587,
  "heritage": 0.68,
  "managed": 0.935,
  "terms": 1.205,
  "material": 0.935,
  "weight": 1.068,
  "status": 0.935,
  "crux": 2.299,
  "allow": 1.395,
  "smothered": 4.668,
  "installations": 3.467,
  "find": 1.405,
  "technically": 1.901,
  "harder": 0.935,
  "retrofit": 4.125,
  "effort": 0.68,
  "road": 1.275,
  "existing": 1.368,
  "flaws": 1.32,
  "rather": 1.383,
  "finding": 0.935,
  "exploiting": 0.911,
  "careful": 0.68,
  "written": 1.068,
  "unintended": 0.312,
  "consequences": 1.245,
  "longer": 1.245,
  "thatched": 7.692,
  "dorset": 0.58,
  "hampshire": 1.103,
  "village": 1.205,
  "cases": 1.245,
  "exemption": 0.582,
  "stands": 0.935,
  "seems": 1.205,
  "loopholes": 0.34,
  "exploitation": 0.68,
  "tightened": 2.366,
  "however": 1.409,
  "purpose": 0.68,
  "amend": 1.068,
  "bring": 1.405,
  "report": 1.347,
  "become": 1.299,
  "law": 1.347,
  "employers": 1.068,
  "run": 1.347,
  "competition": 0.68,
  "schoolchildren": 1.663,
  "draw": 0.68,
  "tackled": 0.537,
  "ecological": 3.231,
  "entries": 2.587,
  "displayed": 1.535,
  "wall": 0.19,
  "office": 1.395,
  "passed": 1.334,
  "looked": 0.935,
  "chosen": 1.068,
  "show": 1.205,
  "contrast": 0.935,
  "page": 0.935,
  "burning": 0.975,
  "world": 1.422,
  "painfully": 1.619,
  "familiar": 1.068,
  "feeds": 1.415,
  "dear": 0.021,
  "friends": 1.245,
  "california": 2.79,
  "alight": 3.117,
  "reminded": 0.68,
  "remember": 1.245,
  "neighbours": 0.935,
  "reeling": 2.267,
  "recent": 1.405,
  "floods": 1.158,
  "children": 1.318,
  "pictures": 2.025,
  "threat": 0.68,
  "showed": 0.935,
  "drew": 1.688,
  "surrounded": 1.023,
  "trees": 1.176,
  "playing": 0.68,
  "fail": 0.935,
  "understood": 0.935,
  "sustainable": 1.368,
  "depends": 0.935,
  "clean": 1.376,
  "mission": 1.334,
  "superpower": 1.13,
  "direct": 0.935,
  "affordable": 1.334,
  "fit": 1.205,
  "simple": 1.299,
  "reliable": 1.205,
  "effective": 1.358,
  "purest": 4.668,
  "converting": 2.67,
  "electrical": 1.849,
  "hands": 1.15,
  "suite": 1.415,
  "alongside": 1.15,
  "offshore": 0.935,
  "underpinned": 0.382,
  "hydrogen": 0.466,
  "decarbonise": 1.544,
  "sectors": 0.68,
  "electrify": 3.004,
  "vast": 1.15,
  "designed": 1.205,
  "yet": 1.368,
  "barely": 0.68,
  "tapped": 3.914,
  "resource": 0.935,
  "aghast": 4.453,
  "mega": 2.144,
  "mw": 3.668,
  "farm": 1.318,
  "proposed": 1.409,
  "blenheim": 3.914,
  "estate": 1.068,
  "allowed": 1.245,
  "developed": 1.245,
  "placing": 0.68,
  "consent": 1.205,
  "transition": 1.275,
  "fully": 1.368,
  "intuitively": 3.914,
  "somewhere": 0.68,
  "kind": 1.068,
  "cash": 1.068,
  "sofa": 2.712,
  "investment": 1.205,
  "reducing": 1.275,
  "professional": 0.68,
  "background": 0.935,
  "accessible": 1.376,
  "easy": 1.318,
  "beneficial": 0.054,
  "models": 0.68,
  "service": 1.368,
  "uttered": 3.117,
  "possibly": 1.205,
  "count": 1.068,
  "putting": 1.376,
  "politics": 1.299,
  "exist": 1.15,
  "surely": 1.205,
  "crucial": 1.334,
  "stop": 1.15,
  "problem": 1.205,
  "solving": 0.879,
  "boost": 1.068,
  "capacity": 1.405,
  "begin": 0.935,
  "dreamed": 2.332,
  "shock": 0.176,
  "decision": 1.068,
  "sunnica": 3.914,
  "ely": 2.299,
  "cambridgeshire": 1.33,
  "despite": 1.245,
  "farming": 0.935,
  "nature": 1.334,
  "sooner": 1.068,
  "lovely": 0.34,
  "glossy": 3.807,
  "leaflets": 1.801,
  "door": 1.205,
  "consultation": 1.4,
  "bigger": 1.068,
  "couple": 1.205,
  "visit": 1.205,
  "noticed": 0.68,
  "hardly": 0.935,
  "dent": 3.117,
  "mid": 0.935,
  "sussex": 0.43,
  "district": 1.275,
  "sitting": 1.15,
  "training": 0.68,
  "basis": 1.299,
  "conservatives": 0.68,
  "greens": 2.332,
  "independents": 3.241,
  "democrats": 1.068,
  "officers": 1.358,
  "ca": 0.106,
  "nppf": 4.66,
  "emergency": 0.935,
  "convince": 0.942,
  "reduce": 1.347,
  "similar": 1.068,
  "revising": 2.115,
  "wanted": 1.245,
  "oxfordshire": 1.788,
  "vale": 1.415,
  "white": 1.068,
  "horse": 1.023,
  "councils": 1.299,
  "brilliant": 1.15,
  "joint": 0.935,
  "obvious": 1.068,
  "delivering": 1.334,
  "ambitious": 1.318,
  "sat": 0.935,
  "authorities": 1.409,
  "empowered": 0.857,
  "ambitions": 0.68,
  "beyond": 1.15,
  "sense": 1.368,
  "adequate": 0.68,
  "end": 1.368,
  "destroying": 0.354,
  "afford": 1.245,
  "bought": 0.68,
  "carefully": 1.275,
  "planned": 0.935,
  "determine": 0.935,
  "whether": 1.438,
  "everything": 1.376,
  "else": 1.245,
  "winter": 1.15,
  "connection": 0.935,
  "certificates": 1.849,
  "casework": 0.623,
  "commend": 1.318,
  "whereby": 0.68,
  "join": 1.205,
  "group": 1.347,
  "diligence": 0.697,
  "supplier": 1.301,
  "contractor": 1.874,
  "discount": 0.727,
  "bulk": 1.247,
  "declaration": 0.176,
  "employer": 0.935,
  "countryside": 0.079,
  "charity": 0.68,
  "supporter": 0.935,
  "passionate": 1.205,
  "rooftop": 5.955,
  "correspondence": 0.68,
  "hertfordshire": 1.455,
  "royston": 3.914,
  "buntingford": 4.032,
  "rapid": 0.68,
  "smaller": 0.935,
  "villages": 1.245,
  "letchworth": 4.474,
  "garden": 0.272,
  "city": 1.15,
  "baldock": 4.162,
  "roughly": 0.764,
  "double": 0.935,
  "challenging": 1.068,
  "balance": 1.299,
  "protection": 0.935,
  "farmland": 1.158,
  "preserving": 1.339,
  "enhancing": 0.41,
  "therefore": 1.334,
  "unsurprising": 2.51,
  "common": 1.275,
  "best": 1.334,
  "finite": 3.029,
  "approach": 1.383,
  "undoubtedly": 0.68,
  "desperately": 0.935,
  "laissez": 3.807,
  "faire": 3.807,
  "significant": 1.389,
  "population": 0.935,
  "grown": 1.15,
  "estates": 0.217,
  "didcot": 2.587,
  "western": 0.68,
  "wantage": 2.803,
  "wallingford": 4.474,
  "wellington": 2.644,
  "gate": 1.514,
  "grove": 1.577,
  "sought": 0.68,
  "create": 1.275,
  "expense": 0.935,
  "suffer": 0.935,
  "potentially": 1.15,
  "profound": 0.935,
  "impacts": 0.68,
  "competing": 0.58,
  "demands": 0.935,
  "fragile": 0.466,
  "security": 1.318,
  "figures": 0.68,
  "megawatt": 3.453,
  "mounted": 4.125,
  "schemes": 0.935,
  "total": 1.068,
  "birmingham": 0.68,
  "bristol": 0.424,
  "manchester": 0.68,
  "liverpool": 0.68,
  "nottingham": 1.081,
  "newcastle": 0.68,
  "leeds": 0.68,
  "academic": 0.014,
  "analysis": 0.935,
  "indicates": 0.682,
  "potential": 1.334,
  "gw": 2.886,
  "dereliction": 1.708,
  "programme": 1.245,
  "since": 1.42,
  "taunton": 1.685,
  "monkton": 4.668,
  "wholehearted": 2.401,
  "agreement": 1.205,
  "generating": 1.035,
  "six": 1.205,
  "strategic": 1.245,
  "beginning": 0.935,
  "provisions": 1.318,
  "host": 0.68,
  "nations": 1.15,
  "proving": 0.727,
  "regulatory": 0.935,
  "currently": 1.275,
  "germany": 0.935,
  "japan": 0.712,
  "enacting": 2.115,
  "legislation": 1.428,
  "accelerate": 0.68,
  "toward": 2.644,
  "meeting": 1.245,
  "industrialisation": 2.401,
  "lowers": 3.378,
  "official": 0.68,
  "multiple": 1.15,
  "quickly": 1.205,
  "empowering": 0.74,
  "families": 1.205,
  "rapidly": 0.935,
  "commercial": 1.15,
  "feed": 1.068,
  "wholesale": 1.211,
  "markets": 0.935,
  "influenced": 1.454,
  "international": 1.275,
  "commodity": 2.436,
  "prices": 0.935,
  "strikes": 0.935,
  "drafted": 0.12,
  "taking": 1.368,
  "pay": 1.299,
  "section": 1.275,
  "negotiations": 1.068,
  "represent": 1.205,
  "led": 1.318,
  "distribution": 0.935,
  "network": 0.935,
  "operator": 0.602,
  "data": 1.068,
  "anyone": 1.334,
  "negotiating": 0.68,
  "position": 0.935,
  "away": 1.4,
  "system": 1.443,
  "cope": 1.068,
  "properties": 1.318,
  "centres": 0.935,
  "warehouses": 3.253,
  "passionately": 0.111,
  "sell": 1.15,
  "keep": 1.205,
  "boundaries": 0.687,
  "mention": 1.205,
  "wait": 1.068,
  "seconds": 1.057,
  "ambition": 1.347,
  "relates": 1.15,
  "solve": 0.935,
  "involving": 0.935,
  "sufficient": 1.15,
  "effectiveness": 0.68,
  "definitely": 1.068,
  "send": 1.068,
  "concerned": 1.245,
  "red": 1.068,
  "tape": 0.935,
  "councillors": 1.245,
  "chamber": 1.068,
  "probably": 1.15,
  "vociferous": 3.378,
  "ones": 1.205,
  "agreements": 0.935,
  "viability": 0.554,
  "telling": 0.68,
  "doctor": 0.935,
  "surgery": 0.935,
  "roads": 1.15,
  "gp": 0.68,
  "surgeries": 0.935,
  "developments": 1.205,
  "west": 1.299,
  "flats": 1.891,
  "practical": 1.299,
  "frustrating": 0.68,
  "drive": 1.299,
  "scaffolding": 3.984,
  "half": 0.935,
  "fill": 1.068,
  "reservations": 2.081,
  "operators": 0.68,
  "harness": 0.942,
  "minded": 0.68,
  "tribute": 1.205,
  "sides": 1.068,
  "tool": 0.68,
  "arsenal": 1.754,
  "properly": 1.205,
  "society": 0.68,
  "seriously": 1.068,
  "amber": 3.598,
  "valley": 1.205,
  "regularly": 0.935,
  "write": 0.935,
  "call": 1.275,
  "eco": 2.115,
  "warriors": 2.332,
  "invariably": 2.003,
  "unopposed": 4.642,
  "unique": 0.68,
  "walked": 0.258,
  "westminster": 0.68,
  "underground": 0.879,
  "station": 1.318,
  "morning": 1.347,
  "billboard": 4.668,
  "caught": 0.68,
  "advertising": 0.452,
  "control": 1.299,
  "borough": 1.358,
  "sold": 1.068,
  "earlier": 1.299,
  "rates": 1.15,
  "wrong": 1.068,
  "target": 1.205,
  "indeed": 1.205,
  "resulting": 0.68,
  "mayor": 1.275,
  "midlands": 0.68,
  "fair": 1.245,
  "committed": 1.368,
  "incorporating": 2.332,
  "cleaner": 1.304,
  "sustainability": 1.068,
  "condition": 0.68,
  "totally": 0.68,
  "perplexing": 4.308,
  "spearheading": 3.533,
  "december": 1.15,
  "lobbying": 0.537,
  "shamefully": 0.742,
  "issued": 0.68,
  "ministerial": 0.935,
  "statement": 1.068,
  "prohibit": 1.229,
  "insisting": 2.087,
  "revoked": 2.587,
  "freedom": 0.68,
  "decarbonising": 2.508,
  "harnessing": 2.087,
  "understands": 0.68,
  "importance": 1.383,
  "wider": 1.15,
  "contribution": 1.15,
  "plays": 0.935,
  "role": 1.405,
  "notion": 0.991,
  "detail": 1.245,
  "raising": 1.068,
  "protective": 0.494,
  "arable": 2.712,
  "social": 1.318,
  "helping": 0.935,
  "greatest": 0.935,
  "paying": 1.068,
  "added": 0.935,
  "examples": 0.935,
  "hart": 3.769,
  "offices": 0.68,
  "kwh": 4.308,
  "leisure": 0.122,
  "sports": 0.68,
  "hall": 0.935,
  "reduces": 0.699,
  "result": 1.318,
  "swimming": 0.975,
  "pool": 0.609,
  "permit": 0.66,
  "sliding": 3.177,
  "doors": 1.205,
  "madam": 1.068,
  "significantly": 1.068,
  "saved": 0.68,
  "region": 1.068,
  "tonnes": 0.449,
  "london": 1.4,
  "sydney": 3.378,
  "return": 1.068,
  "flights": 0.48,
  "grow": 1.068,
  "furthermore": 0.935,
  "increases": 0.935,
  "elsewhere": 0.935,
  "fields": 0.114,
  "critical": 1.15,
  "prioritises": 1.376,
  "mailbag": 4.308,
  "ideas": 0.935,
  "messages": 0.108,
  "advocating": 0.327,
  "experts": 1.068,
  "yesterday": 0.935,
  "scientist": 3.397,
  "wirral": 2.401,
  "architect": 2.366,
  "colin": 1.754,
  "usher": 2.712,
  "combine": 2.285,
  "intelligent": 2.255,
  "bear": 0.935,
  "super": 0.068,
  "triple": 0.39,
  "glazing": 4.032,
  "pays": 0.68,
  "expect": 1.205,
  "pocket": 0.682,
  "tripling": 2.401,
  "gb": 0.186,
  "supports": 1.15,
  "pledges": 1.356,
  "approving": 1.874,
  "projects": 1.205,
  "note": 1.299,
  "week": 1.299,
  "consented": 3.029,
  "entire": 0.935,
  "marked": 0.0,
  "sorely": 1.556,
  "meaningful": 0.935,
  "respect": 1.318,
  "rhetoric": 0.68,
  "weapons": 0.68,
  "borders": 0.68,
  "care": 1.245,
  "likes": 0.68,
  "media": 1.068,
  "viral": 3.241,
  "clip": 3.117,
  "goes": 1.205,
  "responds": 0.396,
  "greener": 1.455,
  "commitments": 1.205,
  "tracts": 4.474,
  "co": 1.15,
  "operation": 0.935,
  "sum": 0.68,
  "game": 0.935,
  "distinct": 0.848,
  "account": 1.318,
  "tom": 0.285,
  "bradshaw": 3.378,
  "president": 0.68,
  "farmers": 1.245,
  "union": 1.15,
  "diversification": 3.059,
  "british": 1.275,
  "raises": 0.935,
  "motivated": 1.019,
  "concern": 1.347,
  "seeing": 1.275,
  "cotswolds": 2.803,
  "beautiful": 0.935,
  "acre": 2.628,
  "provoked": 3.117,
  "outrage": 0.494,
  "objections": 2.109,
  "nearby": 0.091,
  "respondents": 1.917,
  "early": 1.15,
  "sacrifice": 0.095,
  "necessary": 1.409,
  "shoes": 1.434,
  "love": 1.068,
  "walks": 1.007,
  "sane": 4.162,
  "encouraging": 1.205,
  "spend": 0.68,
  "enjoying": 0.217,
  "outdoors": 2.899,
  "mental": 1.15,
  "physical": 1.15,
  "health": 1.318,
  "strengthening": 1.068,
  "relationship": 0.935,
  "humans": 1.777,
  "rest": 0.935,
  "cherished": 1.474,
  "walk": 0.935,
  "instead": 1.275,
  "black": 0.68,
  "shiny": 3.555,
  "adds": 0.935,
  "insult": 0.942,
  "injury": 0.019,
  "sherston": 5.19,
  "massive": 1.205,
  "springing": 4.162,
  "goals": 0.935,
  "collaboration": 1.068,
  "opposition": 1.275,
  "introduce": 1.245,
  "emphasises": 1.801,
  "engagement": 1.299,
  "something": 1.334,
  "imposed": 1.068,
  "corporate": 0.68,
  "thousands": 1.205,
  "worried": 1.15,
  "happier": 1.713,
  "knew": 1.068,
  "buy": 1.15,
  "gaining": 1.073,
  "decreasing": 1.977,
  "reliance": 1.068,
  "vulnerable": 0.935,
  "depending": 0.697,
  "trusted": 0.68,
  "ever": 1.15,
  "sensible": 1.245,
  "term": 1.245,
  "emphasis": 0.037,
  "dividing": 2.003,
  "prioritise": 0.935,
  "greenfield": 3.397,
  "sites": 1.383,
  "delivered": 1.205,
  "strain": 1.068,
  "improves": 1.295,
  "overall": 1.245,
  "resilience": 1.068,
  "wasteful": 2.507,
  "connections": 1.068,
  "ranks": 1.357,
  "pylons": 2.442,
  "marching": 2.087,
  "costly": 1.068,
  "disruptive": 0.991,
  "europe": 0.68,
  "eu": 0.935,
  "goal": 1.068,
  "dependence": 1.415,
  "russian": 0.68,
  "improving": 1.068,
  "self": 0.935,
  "pleasure": 1.15,
  "visiting": 0.68,
  "kettering": 3.062,
  "worries": 0.452,
  "manifesto": 0.935,
  "britain": 1.334,
  "pledged": 0.935,
  "onshore": 1.04,
  "quadruple": 2.95,
  "prouder": 2.548,
  "weeks": 1.275,
  "portcullis": 2.803,
  "lifted": 0.231,
  "ban": 0.68,
  "established": 1.15,
  "delivery": 1.068,
  "especially": 1.334,
  "mine": 1.299,
  "fastest": 1.15,
  "shines": 2.947,
  "contacted": 1.15,
  "aim": 1.15,
  "desire": 0.68,
  "voice": 1.15,
  "hosting": 0.68,
  "strangers": 1.977,
  "irresponsible": 0.354,
  "hand": 1.318,
  "shirk": 3.533,
  "responsibilities": 1.068,
  "met": 0.935,
  "lesson": 0.68,
  "biggest": 0.935,
  "unlocking": 0.34,
  "recognising": 1.068,
  "enhance": 1.068,
  "valued": 0.68,
  "landscapes": 1.891,
  "recognise": 1.383,
  "character": 0.0,
  "beauty": 0.285,
  "record": 1.245,
  "global": 0.68,
  "temperature": 1.825,
  "limit": 0.935,
  "milestone": 1.384,
  "stark": 0.68,
  "reminder": 0.935,
  "leave": 0.935,
  "stone": 0.68,
  "unturned": 2.003,
  "systemic": 0.68,
  "changes": 1.413,
  "safe": 1.068,
  "easiest": 2.031,
  "story": 0.935,
  "leaders": 0.935,
  "deployment": 0.426,
  "sponsored": 0.864,
  "innovation": 1.15,
  "abundant": 2.899,
  "amounts": 0.935,
  "universally": 1.556,
  "major": 1.368,
  "thirds": 1.15,
  "remainder": 1.376,
  "ramp": 1.376,
  "hard": 1.358,
  "remaining": 0.935,
  "goodness": 0.551,
  "sake": 0.935,
  "designer": 3.117,
  "grand": 0.621,
  "designs": 2.987,
  "presenter": 2.95,
  "kevin": 1.247,
  "mccloud": 3.914,
  "wrote": 0.68,
  "rocketed": 2.115,
  "organisation": 0.68,
  "calculated": 0.58,
  "pumps": 1.577,
  "decreases": 4.127,
  "gather": 0.603,
  "neither": 0.935,
  "los": 3.914,
  "angeles": 3.914,
  "wildfires": 4.127,
  "track": 1.068,
  "history": 1.245,
  "heartbreaking": 0.68,
  "losses": 0.68,
  "exceed": 1.23,
  "billion": 0.935,
  "failing": 0.68,
  "line": 1.068,
  "science": 0.935,
  "dwarf": 3.453,
  "proofing": 3.501,
  "moral": 0.68,
  "acting": 0.68,
  "unequivocal": 1.193,
  "homebuyers": 3.709,
  "loans": 0.833,
  "retail": 0.68,
  "lenders": 1.977,
  "deployments": 2.628,
  "linked": 0.68,
  "finance": 0.68,
  "mortgages": 0.777,
  "capital": 0.68,
  "incentivise": 0.354,
  "choices": 0.935,
  "forgive": 0.68,
  "shining": 0.879,
  "sunlight": 3.348,
  "mini": 0.742,
  "rebalance": 1.925,
  "choose": 1.275,
  "revolution": 0.124,
  "choosing": 0.935,
  "vested": 1.176,
  "unsustainable": 0.68,
  "profits": 0.68,
  "guided": 0.942,
  "strides": 1.211,
  "combating": 1.247,
  "wherever": 1.205,
  "later": 1.318,
  "approved": 1.15,
  "stalled": 1.211,
  "lincolnshire": 0.566,
  "anglia": 1.338,
  "capable": 0.68,
  "intent": 1.068,
  "newly": 0.935,
  "achieved": 1.068,
  "alone": 1.299,
  "intervention": 1.334,
  "shortly": 1.068,
  "broadly": 0.68,
  "sentiment": 0.544,
  "aims": 1.205,
  "promoting": 0.935,
  "undeniable": 2.144,
  "larger": 1.068,
  "spectrum": 0.6,
  "constrained": 0.864,
  "orientation": 3.984,
  "structural": 0.223,
  "limitations": 0.848,
  "individual": 1.205,
  "optimised": 3.533,
  "output": 0.757,
  "economies": 1.15,
  "maintain": 0.935,
  "centralise": 3.618,
  "notably": 0.317,
  "ratio": 2.347,
  "unit": 0.68,
  "generated": 0.68,
  "highly": 0.68,
  "scalable": 3.914,
  "exactly": 1.15,
  "subsidy": 1.141,
  "solution": 0.68,
  "versus": 0.978,
  "diverse": 1.068,
  "broad": 0.935,
  "solutions": 0.935,
  "pro": 0.68,
  "thousand": 0.958,
  "actively": 0.935,
  "declare": 1.245,
  "touch": 1.068,
  "photograph": 2.401,
  "pylon": 5.822,
  "window": 0.523,
  "meanwhile": 0.935,
  "grew": 1.15,
  "regime": 0.68,
  "constrains": 4.474,
  "sees": 0.935,
  "lag": 2.628,
  "following": 1.205,
  "tear": 1.454,
  "barriers": 1.358,
  "unlock": 0.68,
  "erewash": 3.231,
  "helped": 0.935,
  "administration": 1.068,
  "blocked": 0.041,
  "information": 0.68,
  "progression": 1.317,
  "pivotal": 0.396,
  "driven": 0.68,
  "held": 1.245,
  "bureaucracy": 0.935,
  "proposals": 1.358,
  "laudable": 1.685,
  "race": 0.68,
  "engaged": 0.68,
  "contest": 1.265,
  "scientific": 0.19,
  "pursuing": 0.68,
  "pride": 0.935,
  "greatly": 0.935,
  "expanding": 1.068,
  "provision": 1.334,
  "acknowledged": 0.68,
  "expansion": 1.15,
  "assured": 0.68,
  "genuine": 0.68,
  "front": 0.935,
  "worthy": 0.231,
  "descriptor": 3.914,
  "immediate": 0.935,
  "certainly": 1.299,
  "neighbour": 1.15,
  "speculate": 1.434,
  "attracted": 1.165,
  "discuss": 0.68,
  "regarding": 1.068,
  "promotion": 0.48,
  "surfaces": 3.378,
  "atop": 4.668,
  "structures": 0.68,
  "moves": 0.68,
  "successfully": 0.68,
  "betterment": 2.757,
  "eloquently": 0.041,
  "pragmatism": 2.51,
  "enjoy": 1.068,
  "undertaking": 0.68,
  "consistently": 1.245,
  "doorsteps": 2.442,
  "tewkesbury": 2.95,
  "considered": 1.15,
  "blindingly": 3.709,
  "antidote": 3.241,
  "rising": 0.68,
  "phasing": 2.267,
  "tended": 2.628,
  "exasperated": 3.004,
  "tone": 0.68,
  "described": 0.935,
  "roundly": 2.95,
  "poll": 1.283,
  "registering": 3.852,
  "vote": 1.476,
  "alignment": 1.711,
  "ball": 0.623,
  "exploring": 0.068,
  "relaunched": 3.453,
  "taskforce": 0.935,
  "map": 0.68,
  "published": 1.245,
  "spring": 0.935,
  "recommendations": 0.935,
  "nearly": 1.15,
  "harm": 0.935,
  "path": 0.935,
  "volatile": 0.697,
  "packages": 1.057,
  "obligation": 0.68,
  "grant": 1.15,
  "fund": 1.068,
  "owners": 1.275,
  "paid": 0.68,
  "surplus": 1.09,
  "smart": 0.494,
  "export": 0.68,
  "guarantee": 0.68,
  "rate": 0.68,
  "vat": 0.261,
  "devolved": 1.448,
  "known": 1.245,
  "welsh": 1.432,
  "gower": 4.987,
  "wales": 1.461,
  "nest": 3.618,
  "improvements": 1.068,
  "eligible": 1.15,
  "states": 1.068,
  "extends": 0.122,
  "aware": 1.334,
  "senedd": 2.485,
  "outcomes": 1.205,
  "highlight": 1.068,
  "tenant": 2.347,
  "treated": 0.68,
  "companies": 0.68,
  "bad": 1.068,
  "actors": 0.935,
  "seek": 1.318,
  "blend": 2.757,
  "workable": 1.193,
  "spokesperson": 0.935,
  "lab": 2.366,
  "constantly": 0.68,
  "merton": 3.059,
  "rule": 0.68,
  "inadequate": 0.68,
  "improvement": 1.15,
  "pushing": 0.68,
  "highest": 0.68,
  "number": 1.405,
  "applications": 1.409,
  "lack": 1.245,
  "skyrocketing": 2.174,
  "disgracefully": 1.777,
  "dithered": 2.803,
  "delayed": 0.935,
  "surprise": 0.935,
  "corrected": 1.187,
  "repair": 0.68,
  "damage": 0.935,
  "contributed": 0.935,
  "barrier": 1.068,
  "acceptance": 1.09,
  "hearing": 1.068,
  "urgently": 0.68,
  "spatial": 3.115,
  "addresses": 0.935,
  "takes": 0.935,
  "horrific": 0.935,
  "raging": 2.803,
  "flooding": 0.935,
  "reminders": 2.548,
  "urgent": 1.068,
  "showing": 0.68,
  "leadership": 1.205,
  "acknowledging": 0.354,
  "parliamentary": 1.443,
  "chaired": 0.68,
  "turning": 0.68,
  "stimulating": 2.436,
  "marks": 0.68,
  "spencer": 1.801,
  "mostyn": 4.162,
  "street": 1.15,
  "llandudno": 5.421,
  "transforming": 0.285,
  "indoor": 2.712,
  "entertainment": 1.474,
  "exciting": 0.68,
  "funded": 0.935,
  "authority": 1.405,
  "emailing": 3.378,
  "arrange": 0.279,
  "reduction": 1.205,
  "boosting": 1.068,
  "implemented": 1.245,
  "soon": 0.935,
  "increasing": 1.245,
  "piece": 1.245,
  "otherwise": 0.935,
  "pv": 7.034,
  "equipment": 0.68,
  "merits": 0.68,
  "shared": 0.935,
  "reaching": 1.068,
  "welcoming": 0.68,
  "outlined": 1.299,
  "constructive": 1.068,
  "strengthened": 1.15,
  "appreciated": 0.074,
  "try": 1.205,
  "ray": 2.981,
  "danger": 0.935,
  "misleading": 0.551,
  "light": 0.68,
  "table": 0.68,
  "amendments": 0.935,
  "aimed": 0.027,
  "advancing": 1.544,
  "rests": 2.314,
  "luck": 0.354,
  "sceptical": 1.32,
  "abilities": 1.301,
  "expanded": 1.068,
  "options": 1.358,
  "renters": 0.58,
  "additionally": 0.653,
  "november": 0.935,
  "ministry": 0.935,
  "announced": 0.68,
  "rights": 1.15,
  "pledge": 0.68,
  "projected": 0.623,
  "chief": 0.68,
  "executive": 0.68,
  "admitted": 0.68,
  "stocks": 1.777,
  "complex": 1.068,
  "tenure": 1.007,
  "owned": 1.068,
  "freeholders": 2.267,
  "occupied": 0.014,
  "leaseholders": 1.535,
  "tenants": 0.623,
  "successive": 0.68,
  "governments": 1.395,
  "updates": 0.13,
  "retrofits": 4.9,
  "realm": 1.176,
  "units": 0.68,
  "obstacle": 1.641,
  "hinder": 1.535,
  "restrictions": 0.935,
  "timescale": 0.48,
  "implement": 1.245,
  "remotely": 1.247,
  "surprising": 0.056,
  "resistant": 2.205,
  "grounds": 0.68,
  "indubitably": 4.668,
  "flipside": 3.807,
  "coin": 2.541,
  "value": 1.275,
  "running": 1.15,
  "elaborate": 1.338,
  "claim": 1.15,
  "various": 1.245,
  "strike": 1.15,
  "maintaining": 1.068,
  "tempting": 1.708,
  "repairs": 0.242,
  "worry": 0.68,
  "consequence": 0.935,
  "frequent": 0.272,
  "requirements": 1.15,
  "embedded": 0.396,
  "administrators": 4.381,
  "task": 1.068,
  "contains": 0.935,
  "approximately": 0.68,
  "chapters": 3.984,
  "guidance": 1.334,
  "reflect": 0.935,
  "examination": 1.007,
  "complexity": 1.275,
  "consideration": 1.068,
  "surface": 0.712,
  "align": 0.623,
  "practices": 1.15,
  "translate": 2.003,
  "real": 1.205,
  "simplify": 1.929,
  "fulfil": 0.68,
  "requiring": 0.68,
  "lengthy": 0.0,
  "procedures": 1.068,
  "prove": 0.68,
  "compliance": 0.68,
  "relevant": 1.068,
  "ready": 0.935,
  "brownfield": 2.522,
  "prioritised": 0.935,
  "sacrificing": 2.548,
  "valuable": 1.245,
  "sincerely": 1.068,
  "feedback": 0.336,
  "access": 1.447,
  "recognised": 0.935,
  "fits": 0.566,
  "lead": 1.068,
  "inefficiencies": 2.51,
  "consultations": 0.327,
  "drafting": 0.802,
  "stakeholders": 1.068,
  "consumer": 0.68,
  "influence": 0.68,
  "representatives": 1.15,
  "committees": 0.935,
  "receives": 0.68,
  "passes": 1.068,
  "scrutinise": 0.935,
  "balances": 0.833,
  "imperative": 0.935,
  "positioning": 2.712,
  "scrutiny": 0.935,
  "sensibly": 2.205,
  "feasible": 2.701,
  "list": 0.935,
  "adapt": 0.599,
  "avoid": 1.245,
  "scrapping": 0.68,
  "reassure": 1.068,
  "reaches": 0.373,
  "comply": 0.935,
  "nice": 0.935,
  "nasty": 2.235,
  "outlines": 0.609,
  "donations": 0.787,
  "tried": 0.935,
  "outline": 0.935,
  "realised": 0.68,
  "initiatives": 0.68,
  "usage": 0.682,
  "address": 1.318,
  "handle": 0.667,
  "article": 1.068,
  "conclude": 1.205,
  "reaffirming": 2.67,
  "realism": 3.004,
  "closer": 0.68,
  "lucky": 0.935,
  "sanctioned": 0.354,
  "becomes": 1.068,
  "presumption": 0.727,
  "supplementing": 2.67,
  "domestic": 0.68,
  "rough": 0.848,
  "adopted": 0.935,
  "watered": 1.663,
  "largely": 1.068,
  "minimal": 0.848,
  "older": 1.299,
  "topics": 0.712,
  "mailbox": 4.668,
  "grandparents": 1.193,
  "meetings": 0.68,
  "attended": 0.935,
  "association": 0.935,
  "supplementary": 1.32,
  "shortage": 0.68,
  "norfolk": 1.068,
  "particular": 1.318,
  "associations": 0.817,
  "broadland": 2.899,
  "constructed": 1.124,
  "mixed": 0.396,
  "containing": 0.718,
  "frustrations": 1.247,
  "constituent": 1.068,
  "complained": 1.577,
  "bird": 2.087,
  "netting": 4.474,
  "deterrents": 2.401,
  "influx": 3.501,
  "pigeons": 4.668,
  "nuisance": 2.41,
  "scene": 0.897,
  "hitchcock": 4.668,
  "film": 0.537,
  "daily": 1.068,
  "easily": 1.068,
  "correctly": 1.15,
  "applied": 1.205,
  "wants": 1.205,
  "thanking": 0.68,
  "namely": 0.261,
  "consumption": 1.229,
  "delivers": 0.68,
  "provides": 1.205,
  "fluctuations": 2.803,
  "touched": 0.68,
  "integral": 0.68,
  "intend": 1.299,
  "introduction": 1.15,
  "proof": 0.935,
  "fabric": 0.66,
  "foster": 0.272,
  "job": 1.068,
  "watching": 0.68,
  "proceedings": 0.68,
  "related": 1.068,
  "objective": 0.935,
  "stem": 1.023,
  "recognition": 0.68,
  "landscape": 0.68,
  "dealt": 0.935,
  "officials": 1.068,
  "achievable": 2.442,
  "primary": 1.275,
  "adverse": 0.41,
  "inherently": 1.685,
  "flawed": 0.244,
  "convinced": 0.68,
  "proceeding": 1.592,
  "shall": 0.935,
  "none": 1.15,
  "providing": 0.935,
  "wrestling": 3.308,
  "refine": 2.332,
  "emerging": 1.205,
  "speak": 1.275,
  "weaknesses": 1.777,
  "entail": 3.501,
  "closed": 1.068,
  "march": 0.68,
  "responses": 0.68,
  "received": 1.205,
  "detailed": 0.68,
  "department": 0.935,
  "amassed": 3.618,
  "acutely": 0.191,
  "succeed": 0.68,
  "crucially": 0.68,
  "dictatorial": 4.668,
  "expert": 0.68,
  "hub": 0.68,
  "considering": 1.205,
  "flexibility": 1.15,
  "invaluable": 0.19,
  "shaping": 0.682,
  "considerations": 0.093,
  "determining": 0.732,
  "precise": 0.093,
  "briefly": 0.935,
  "illustrate": 1.688,
  "sort": 1.068,
  "weighing": 2.67,
  "forthcoming": 1.068,
  "requirement": 1.275,
  "option": 1.405,
  "elements": 0.68,
  "equating": 3.004,
  "inclusion": 0.68,
  "coverage": 0.264,
  "argued": 0.68,
  "virtually": 0.244,
  "impossible": 0.935,
  "types": 0.935,
  "windows": 1.494,
  "clause": 0.935,
  "sets": 1.068,
  "explored": 1.229,
  "submitted": 0.68,
  "concluded": 0.68,
  "importantly": 1.15,
  "needing": 0.0,
  "turn": 1.15,
  "cause": 1.068,
  "unmanageable": 3.004,
  "workloads": 2.899,
  "bottlenecks": 3.177,
  "rolled": 0.68,
  "trivial": 2.366,
  "features": 0.508,
  "shape": 0.935,
  "pitch": 1.176,
  "reasonably": 0.081,
  "exercise": 1.299,
  "resourced": 0.041,
  "carry": 1.068,
  "numbers": 1.205,
  "enforcement": 0.935,
  "mechanism": 0.935,
  "instances": 0.68,
  "unscrupulous": 1.376,
  "fall": 0.68,
  "overstretched": 1.102,
  "alive": 0.68,
  "determined": 0.935,
  "timeframe": 0.396,
  "stipulates": 3.378,
  "prepare": 0.935,
  "accompanying": 1.874,
  "statutory": 0.68,
  "preparing": 1.15,
  "insignificant": 2.366,
  "upon": 0.68,
  "protocol": 0.864,
  "finalised": 1.874,
  "affirmative": 3.365,
  "resolution": 1.068,
  "unlikely": 0.935,
  "earliest": 0.081,
  "redesign": 2.95,
  "prepared": 0.935,
  "pertinent": 0.48,
  "medium": 0.68,
  "sized": 0.68,
  "enterprises": 0.68,
  "deadline": 0.231,
  "unviable": 2.087,
  "wasted": 0.68,
  "negative": 1.205,
  "disruption": 1.068,
  "numerous": 0.68,
  "transitional": 1.614,
  "arrangements": 1.389,
  "typically": 0.258,
  "minimise": 0.935,
  "associated": 1.275,
  "completed": 1.068,
  "month": 1.15,
  "laying": 0.205,
  "followed": 1.205,
  "meant": 1.205,
  "contradict": 2.401,
  "override": 1.641,
  "main": 0.935,
  "premise": 1.283,
  "principle": 0.935,
  "micro": 2.235,
  "urgency": 0.935,
  "immense": 1.068,
  "raining": 3.177,
  "parade": 1.663,
  "proceed": 1.068,
  "route": 1.205,
  "slower": 1.731,
  "gently": 0.68,
  "idea": 0.935,
  "leaving": 0.68,
  "minor": 0.037,
  "robust": 0.935,
  "involves": 1.068,
  "structured": 1.619,
  "deliverable": 1.685,
  "coherent": 0.697,
  "arguably": 0.927,
  "faster": 0.68,
  "achieving": 0.935,
  "reflecting": 0.68,
  "afraid": 0.68,
  "revise": 1.977,
  "strengthen": 1.068,
  "levy": 0.68,
  "devised": 2.628,
  "respects": 0.68,
  "consistency": 0.099,
  "withdrawn": 0.108,
  "understandably": 0.68,
  "left": 0.935,
  "reluctant": 0.667,
  "invest": 0.68,
  "announcement": 0.68,
  "anticipation": 1.977,
  "conflicting": 2.332,
  "confusion": 1.275,
  "risks": 0.68,
  "reversing": 0.802,
  "momentum": 1.32,
  "establish": 0.68,
  "firm": 0.68,
  "legislate": 0.935,
  "arrive": 0.68,
  "judgment": 0.68,
  "efficacy": 1.801,
  "distant": 0.957,
  "germans": 2.757,
  "balconies": 4.668,
  "looks": 0.68,
  "reiterate": 0.935,
  "thanks": 1.15,
  "commendable": 1.514,
  "appreciate": 1.068,
  "dedicated": 1.068,
  "assuming": 1.395,
  "dialogue": 0.68,
  "closely": 1.245,
  "prior": 1.068,
  "incorporated": 2.138,
  "objectives": 0.935,
  "divide": 0.68,
  "christian": 0.48,
  "wakeford": 2.587,
  "amendment": 1.068,
  "licensing": 1.447,
  "vibrant": 0.019,
  "hospitality": 1.413,
  "momentous": 3.348,
  "moments": 1.245,
  "deliberations": 1.825,
  "changing": 1.15,
  "procedure": 1.299,
  "extensions": 4.129,
  "career": 1.068,
  "venues": 1.178,
  "focal": 2.712,
  "fundamental": 1.205,
  "cohesion": 0.897,
  "adults": 0.68,
  "combatting": 4.308,
  "loneliness": 1.777,
  "according": 0.935,
  "wrexham": 3.532,
  "finest": 0.895,
  "beers": 3.807,
  "acton": 2.587,
  "lion": 2.609,
  "crown": 0.68,
  "quarry": 2.51,
  "buck": 1.09,
  "bangor": 4.526,
  "dee": 3.241,
  "cunliffe": 3.117,
  "george": 0.68,
  "dragon": 3.378,
  "golden": 0.362,
  "kings": 2.087,
  "drinks": 1.708,
  "operated": 0.176,
  "groups": 1.245,
  "mr": 1.068,
  "ranger": 5.719,
  "returns": 0.68,
  "feet": 0.68,
  "obviously": 1.15,
  "weald": 2.712,
  "feeling": 0.68,
  "pub": 0.497,
  "names": 0.68,
  "named": 0.68,
  "span": 2.548,
  "personally": 0.68,
  "tourism": 1.15,
  "contributes": 0.48,
  "similarly": 0.935,
  "true": 1.15,
  "arrival": 1.187,
  "hollywood": 2.85,
  "welcomed": 0.68,
  "visitors": 1.068,
  "afield": 1.357,
  "eager": 1.641,
  "afc": 3.241,
  "famous": 0.014,
  "racecourse": 3.004,
  "pulled": 0.935,
  "pint": 2.314,
  "landlord": 1.229,
  "wayne": 2.899,
  "turf": 3.807,
  "accommodating": 2.436,
  "never": 1.245,
  "cafes": 5.231,
  "restaurants": 1.475,
  "hotels": 0.203,
  "stepping": 0.68,
  "plate": 1.731,
  "staff": 1.245,
  "drink": 0.272,
  "round": 0.935,
  "ability": 1.275,
  "extending": 0.935,
  "blanket": 1.43,
  "thereby": 0.298,
  "allowing": 1.245,
  "licensed": 2.51,
  "premises": 1.245,
  "celebration": 1.317,
  "telegraph": 1.176,
  "interview": 0.712,
  "conducted": 0.68,
  "interviewing": 3.453,
  "residing": 3.308,
  "moon": 2.378,
  "watford": 1.849,
  "implications": 0.935,
  "journalism": 1.899,
  "valid": 0.935,
  "stay": 1.205,
  "event": 1.245,
  "normal": 1.068,
  "circumstances": 1.068,
  "temporary": 1.275,
  "application": 1.42,
  "administrative": 0.064,
  "twofold": 3.378,
  "meaning": 0.68,
  "late": 1.275,
  "occasions": 1.245,
  "royal": 1.299,
  "weddings": 4.283,
  "sporting": 1.395,
  "events": 1.405,
  "men": 1.068,
  "football": 1.245,
  "squad": 2.757,
  "reached": 1.068,
  "finals": 3.501,
  "euros": 2.205,
  "trauma": 0.68,
  "penalties": 0.68,
  "anticipated": 0.582,
  "jubilation": 4.9,
  "cup": 1.007,
  "fa": 1.925,
  "situation": 1.15,
  "complicated": 0.935,
  "team": 1.245,
  "checking": 2.56,
  "lamentable": 3.177,
  "closure": 1.068,
  "seven": 0.935,
  "stars": 1.731,
  "preston": 2.115,
  "reopening": 1.144,
  "clock": 0.935,
  "tonight": 0.68,
  "celebrating": 1.068,
  "covid": 0.68,
  "extraordinary": 0.68,
  "hoops": 2.803,
  "jumped": 1.95,
  "seeks": 1.299,
  "basically": 0.023,
  "lives": 1.068,
  "secondary": 0.935,
  "approve": 0.149,
  "recess": 1.245,
  "lionesses": 3.205,
  "august": 0.68,
  "historic": 0.68,
  "unforgettable": 3.709,
  "occasion": 1.205,
  "continued": 0.68,
  "teams": 1.205,
  "arises": 1.09,
  "upcoming": 1.15,
  "fifa": 5.976,
  "america": 0.68,
  "rugby": 0.776,
  "australia": 0.68,
  "women": 1.068,
  "brazil": 2.174,
  "cricket": 1.434,
  "india": 0.068,
  "sri": 2.899,
  "lanka": 3.177,
  "successes": 1.144,
  "scottish": 1.459,
  "northern": 0.68,
  "irish": 0.68,
  "tough": 0.935,
  "plummeted": 1.874,
  "parliamentarians": 0.935,
  "affords": 2.85,
  "behalf": 0.68,
  "flexible": 0.935,
  "somebody": 0.68,
  "washing": 2.003,
  "pots": 1.301,
  "orders": 1.299,
  "controversy": 1.977,
  "dissent": 0.942,
  "objecting": 2.712,
  "extension": 1.299,
  "wedding": 2.609,
  "objected": 2.174,
  "pray": 1.535,
  "mechanics": 2.757,
  "operate": 0.68,
  "decided": 0.68,
  "exceptional": 1.068,
  "significance": 1.068,
  "word": 0.935,
  "alter": 1.505,
  "notices": 0.508,
  "glass": 0.638,
  "brief": 0.935,
  "basildon": 3.874,
  "billericay": 5.367,
  "chequers": 4.308,
  "modern": 1.205,
  "bar": 0.68,
  "laindon": 6.414,
  "brewery": 3.366,
  "shapes": 1.874,
  "sizes": 1.007,
  "landlords": 0.424,
  "institutions": 0.68,
  "faced": 1.15,
  "parliamentarian": 1.158,
  "award": 0.68,
  "draught": 3.241,
  "relief": 0.68,
  "simplifying": 2.68,
  "bind": 1.849,
  "insurance": 1.068,
  "presents": 0.935,
  "targeted": 0.935,
  "instil": 2.366,
  "resilient": 0.935,
  "mp": 1.245,
  "unite": 0.298,
  "runs": 0.935,
  "deep": 0.68,
  "mason": 4.308,
  "denbigh": 4.032,
  "colwyn": 4.308,
  "hubs": 0.68,
  "culture": 0.68,
  "clwyd": 1.925,
  "closing": 0.68,
  "concerning": 0.935,
  "locals": 2.003,
  "champion": 0.68,
  "games": 0.888,
  "parc": 3.807,
  "diminishing": 1.849,
  "fairness": 0.68,
  "ease": 1.15,
  "pressures": 1.275,
  "bolster": 0.682,
  "appg": 0.523,
  "aberconwy": 4.893,
  "breweries": 3.916,
  "filled": 0.68,
  "taste": 2.115,
  "albion": 2.899,
  "conwy": 3.533,
  "seriousness": 0.935,
  "streamline": 1.616,
  "staying": 0.566,
  "spirit": 0.68,
  "northampton": 3.778,
  "varied": 1.124,
  "employ": 0.935,
  "fortunate": 0.935,
  "visits": 0.68,
  "leap": 1.777,
  "eastern": 0.327,
  "reopened": 1.007,
  "disastrous": 0.935,
  "river": 0.68,
  "nene": 4.308,
  "britannia": 3.378,
  "camera": 2.174,
  "barman": 4.668,
  "houghton": 2.85,
  "everard": 4.203,
  "famously": 1.556,
  "carlsberg": 4.9,
  "served": 0.935,
  "serves": 0.68,
  "special": 1.205,
  "resides": 3.453,
  "border": 0.935,
  "neighbouring": 1.205,
  "lucy": 1.193,
  "rigby": 3.618,
  "nationally": 0.68,
  "changed": 1.068,
  "fans": 1.164,
  "follow": 0.68,
  "saints": 2.299,
  "players": 0.833,
  "called": 1.068,
  "extended": 1.245,
  "watch": 0.935,
  "safety": 0.68,
  "prevent": 1.15,
  "beautifully": 2.235,
  "backs": 0.014,
  "tradition": 0.68,
  "secondly": 1.15,
  "income": 0.68,
  "streets": 0.68,
  "spots": 2.174,
  "finally": 0.935,
  "relieve": 1.357,
  "spent": 0.935,
  "relieved": 0.958,
  "regular": 0.935,
  "patron": 2.587,
  "stockton": 1.839,
  "progressed": 1.09,
  "request": 1.299,
  "denying": 0.452,
  "licences": 0.68,
  "punters": 4.162,
  "swiftly": 0.68,
  "retaining": 0.424,
  "safeguards": 0.68,
  "measured": 0.68,
  "resolve": 1.068,
  "mighty": 1.685,
  "appearance": 1.813,
  "champions": 0.217,
  "league": 0.68,
  "meantime": 0.68,
  "express": 1.068,
  "tournament": 4.632,
  "intoxicated": 4.474,
  "degree": 0.935,
  "outset": 0.68,
  "facilitate": 1.068,
  "passage": 1.068,
  "compelling": 0.122,
  "relaxes": 4.9,
  "determines": 1.977,
  "meets": 0.935,
  "criteria": 0.68,
  "specify": 1.107,
  "dates": 0.108,
  "relaxations": 4.9,
  "thus": 0.68,
  "revenue": 0.68,
  "thirdly": 0.935,
  "licence": 0.68,
  "individually": 0.879,
  "automatically": 0.0,
  "saves": 1.247,
  "fee": 0.712,
  "falkirk": 2.45,
  "benefited": 0.68,
  "euro": 2.177,
  "tartan": 3.709,
  "army": 0.68,
  "workers": 0.68,
  "endorse": 0.43,
  "safely": 0.935,
  "protected": 1.068,
  "workforce": 0.68,
  "relaxed": 2.436,
  "profile": 0.108,
  "majesty": 0.935,
  "coronation": 2.67,
  "queen": 0.68,
  "birthday": 0.149,
  "platinum": 3.914,
  "jubilee": 2.85,
  "specifies": 2.058,
  "paced": 3.914,
  "problematic": 0.727,
  "participation": 1.395,
  "competitions": 2.436,
  "uncertain": 0.122,
  "usual": 0.935,
  "channels": 0.742,
  "emphasise": 1.068,
  "summer": 1.299,
  "equally": 0.935,
  "commendably": 3.807,
  "rectify": 1.117,
  "deregulating": 4.668,
  "hair": 1.376,
  "discussing": 1.068,
  "content": 0.68,
  "hour": 0.68,
  "sparingly": 3.807,
  "frequency": 1.429,
  "powers": 1.205,
  "invoked": 2.899,
  "policing": 0.935,
  "fire": 1.15,
  "crime": 1.245,
  "prevention": 0.68,
  "police": 1.376,
  "disorder": 1.15,
  "attributable": 1.556,
  "drinking": 1.107,
  "previously": 1.068,
  "utmost": 0.095,
  "ample": 1.998,
  "firmly": 1.15,
  "continuing": 0.68,
  "advance": 1.068,
  "conclusion": 1.15,
  "spoken": 1.245,
  "celebrations": 1.514,
  "andrew": 0.935,
  "learned": 0.68,
  "comments": 1.15,
  "summary": 0.466,
  "introduces": 0.638,
  "cut": 1.15,
  "agreed": 1.205,
  "accordingly": 0.935,
  "electors": 5.073,
  "democracy": 1.416,
  "person": 1.334,
  "october": 1.15,
  "online": 1.457,
  "absent": 1.067,
  "voting": 1.467,
  "services": 1.441,
  "launched": 1.068,
  "postal": 3.582,
  "proxy": 3.294,
  "united": 1.318,
  "kingdom": 1.318,
  "elections": 1.481,
  "commissioner": 1.15,
  "launch": 1.068,
  "digital": 1.389,
  "elector": 4.668,
  "processed": 0.998,
  "inconsistency": 2.848,
  "equal": 1.15,
  "cymru": 1.566,
  "please": 0.68,
  "seated": 2.058,
  "ms": 0.653,
  "gilbert": 3.177,
  "encouragement": 0.742,
  "democratic": 1.425,
  "yes": 0.68,
  "gould": 3.533,
  "review": 1.15,
  "disabled": 0.935,
  "holding": 0.68,
  "electoral": 1.391,
  "alike": 0.081,
  "polls": 2.138,
  "forcing": 0.68,
  "wished": 1.475,
  "devolution": 1.334,
  "bodies": 0.935,
  "legislative": 1.205,
  "duly": 2.51,
  "votes": 1.422,
  "digitally": 3.365,
  "aspects": 1.068,
  "identity": 0.68,
  "voter": 3.658,
  "identification": 1.081,
  "polling": 1.545,
  "photographic": 3.004,
  "check": 0.68,
  "applicant": 1.95,
  "applies": 1.068,
  "reserved": 1.303,
  "cycles": 2.347,
  "refresh": 1.849,
  "signature": 2.867,
  "reapply": 3.618,
  "arrangement": 1.068,
  "confusing": 2.217,
  "file": 2.003,
  "element": 0.68,
  "divergence": 3.675,
  "remove": 1.205,
  "burdens": 0.935,
  "inconsistencies": 2.144,
  "transparent": 0.68,
  "turnout": 4.476,
  "dropping": 0.911,
  "legislators": 1.598,
  "respected": 0.68,
  "component": 0.354,
  "ill": 0.68,
  "whose": 1.068,
  "ageing": 1.04,
  "demographic": 1.891,
  "restriction": 0.772,
  "conduct": 0.68,
  "manageable": 2.205,
  "complicating": 3.914,
  "single": 1.275,
  "transferable": 4.191,
  "spite": 1.474,
  "methods": 0.68,
  "encountered": 1.474,
  "anything": 1.245,
  "complication": 3.984,
  "respectful": 0.895,
  "settlement": 0.68,
  "enact": 1.265,
  "rose": 1.068,
  "permanently": 0.258,
  "spoilt": 4.308,
  "signing": 0.317,
  "perpetuity": 2.144,
  "enacted": 0.336,
  "consistent": 1.205,
  "asking": 0.935,
  "awful": 0.68,
  "explaining": 0.508,
  "confirmation": 0.162,
  "extra": 1.15,
  "returning": 1.318,
  "fife": 1.193,
  "wasting": 0.848,
  "candidates": 0.66,
  "simpler": 1.117,
  "doorstep": 0.633,
  "begun": 0.68,
  "knocking": 1.659,
  "citizens": 1.15,
  "explained": 0.935,
  "helpful": 0.935,
  "presiding": 1.708,
  "officer": 1.068,
  "sorry": 0.68,
  "habits": 1.357,
  "die": 0.68,
  "glasgow": 1.299,
  "largest": 0.68,
  "registered": 1.347,
  "reflects": 1.068,
  "hindered": 2.587,
  "casting": 2.51,
  "overly": 0.942,
  "registers": 2.828,
  "processes": 1.299,
  "edinburgh": 1.275,
  "leith": 5.131,
  "student": 0.935,
  "accommodation": 1.15,
  "remains": 1.245,
  "incumbent": 0.468,
  "promote": 0.68,
  "engage": 1.205,
  "accessibility": 0.69,
  "students": 1.245,
  "engaging": 1.205,
  "isolated": 0.935,
  "incidents": 0.68,
  "holidays": 1.62,
  "booked": 2.587,
  "speedier": 3.914,
  "colinton": 4.668,
  "oxgangs": 5.19,
  "seasons": 2.712,
  "realise": 0.68,
  "intervening": 0.667,
  "autumn": 0.935,
  "fewer": 0.68,
  "daylight": 2.548,
  "colder": 2.85,
  "dark": 0.68,
  "blind": 1.068,
  "partially": 1.818,
  "screen": 1.338,
  "readers": 2.436,
  "lifts": 1.434,
  "involvement": 0.935,
  "modernised": 2.174,
  "parliaments": 0.956,
  "saddened": 2.314,
  "surprised": 1.068,
  "snp": 0.68,
  "affects": 0.68,
  "asks": 0.935,
  "via": 1.068,
  "locked": 0.68,
  "exercising": 0.857,
  "purely": 0.108,
  "writing": 0.935,
  "interacting": 3.177,
  "comfortable": 0.203,
  "agreeing": 0.68,
  "unusual": 0.068,
  "accessing": 1.068,
  "disengagement": 3.453,
  "participate": 1.299,
  "useful": 0.68,
  "chartist": 4.9,
  "woman": 0.935,
  "civic": 1.007,
  "backbone": 0.261,
  "enabled": 0.68,
  "whichever": 1.048,
  "pointed": 0.935,
  "anomaly": 1.514,
  "limits": 0.68,
  "equality": 1.068,
  "continues": 0.935,
  "urging": 0.68,
  "schoolteacher": 3.914,
  "message": 1.068,
  "unable": 1.245,
  "disability": 0.68,
  "remote": 0.258,
  "consuming": 1.283,
  "parity": 0.727,
  "unfair": 0.68,
  "deterred": 2.442,
  "encounter": 1.641,
  "contribute": 0.935,
  "disparity": 1.04,
  "disincentivising": 3.709,
  "smooth": 1.43,
  "reputation": 0.68,
  "strongest": 0.68,
  "democracies": 1.176,
  "shut": 0.68,
  "disrespect": 2.031,
  "whoever": 0.34,
  "voted": 1.15,
  "manner": 1.068,
  "approached": 0.231,
  "aligns": 1.376,
  "partners": 0.68,
  "collectively": 0.68,
  "modernise": 0.578,
  "swansea": 1.899,
  "fellow": 1.068,
  "incredulous": 3.914,
  "unavailable": 2.628,
  "deficit": 0.68,
  "addressed": 0.935,
  "transport": 1.245,
  "weather": 0.068,
  "university": 1.205,
  "hugely": 0.935,
  "interaction": 1.331,
  "shouted": 2.899,
  "occasionally": 0.958,
  "linking": 0.895,
  "actual": 0.68,
  "institute": 0.68,
  "demonstrates": 0.68,
  "satisfied": 1.068,
  "smoother": 2.95,
  "rnib": 5.719,
  "campaigned": 0.935,
  "loss": 1.068,
  "desires": 3.059,
  "clerks": 0.837,
  "confident": 0.935,
  "candidate": 0.041,
  "assembly": 0.68,
  "registration": 0.633,
  "statistics": 0.68,
  "classes": 1.247,
  "computing": 2.587,
  "stacks": 4.971,
  "cards": 1.208,
  "internet": 0.122,
  "underestimate": 1.023,
  "difficulty": 0.68,
  "autistic": 2.611,
  "anxiety": 0.68,
  "complications": 1.788,
  "neurodiverse": 4.447,
  "approval": 0.68,
  "prefer": 0.396,
  "justify": 0.68,
  "discrepancies": 2.757,
  "doctors": 0.68,
  "employee": 0.438,
  "variation": 1.474,
  "sunderland": 1.357,
  "lewisham": 2.757,
  "someone": 1.068,
  "ballot": 1.584,
  "explanatory": 0.848,
  "notes": 0.68,
  "discrepancy": 2.85,
  "knock": 0.68,
  "anybody": 0.935,
  "activists": 0.566,
  "natives": 4.9,
  "listen": 0.68,
  "excluded": 1.068,
  "copies": 1.754,
  "mother": 1.068,
  "smartphones": 2.174,
  "qr": 5.719,
  "code": 0.935,
  "phone": 1.068,
  "opens": 1.107,
  "goodbye": 1.977,
  "completion": 0.833,
  "handing": 0.757,
  "suggest": 0.68,
  "website": 0.68,
  "baby": 0.68,
  "crying": 0.027,
  "dinner": 1.32,
  "burn": 1.801,
  "likely": 1.15,
  "occurred": 0.68,
  "chaos": 0.68,
  "fell": 0.68,
  "deeply": 0.68,
  "disadvantaged": 0.68,
  "disenfranchised": 4.4,
  "broken": 0.68,
  "imminent": 0.927,
  "terrible": 0.68,
  "dealing": 0.68,
  "english": 1.205,
  "levels": 1.15,
  "explains": 1.357,
  "scenarios": 1.971,
  "separate": 0.68,
  "stressed": 0.848,
  "apart": 0.68,
  "apologise": 0.68,
  "experienced": 0.68,
  "stray": 2.436,
  "alleged": 0.354,
  "topic": 0.68,
  "chap": 2.899,
  "countless": 0.935,
  "id": 2.249,
  "swear": 3.618,
  "persuasion": 2.267,
  "participated": 0.802,
  "guaranteed": 0.68,
  "stainbank": 5.096,
  "substance": 0.68,
  "clarity": 0.935,
  "cast": 1.15,
  "contradiction": 1.535,
  "sits": 0.68,
  "seeking": 0.68,
  "warrants": 1.556,
  "remarkably": 1.64,
  "poor": 0.68,
  "cited": 0.48,
  "researching": 2.712,
  "seat": 0.68,
  "valuation": 2.587,
  "standardising": 5.719,
  "electorate": 1.331,
  "misapprehension": 4.308,
  "competently": 4.308,
  "mum": 1.068,
  "olds": 0.0,
  "encompassing": 3.378,
  "exam": 3.32,
  "periods": 0.935,
  "occur": 0.68,
  "stress": 1.068,
  "driving": 0.68,
  "impression": 0.653,
  "commission": 1.376,
  "integrity": 1.15,
  "avoiding": 0.551,
  "arbitrary": 0.64,
  "feature": 0.68,
  "rebuild": 0.935,
  "unduly": 1.663,
  "converge": 3.914,
  "eligibility": 0.122,
  "depression": 1.176,
  "cured": 3.453,
  "examiner": 3.618,
  "qualifications": 0.135,
  "scheduled": 0.911,
  "exact": 0.68,
  "julia": 2.299,
  "hartley": 3.533,
  "brewer": 3.709,
  "headline": 0.34,
  "stating": 0.299,
  "disaster": 0.935,
  "delight": 1.283,
  "pals": 3.807,
  "flocking": 4.668,
  "fix": 0.68,
  "theoretical": 2.299,
  "field": 0.68,
  "seats": 0.727,
  "reflected": 0.68,
  "timing": 0.258,
  "disproportionately": 0.68,
  "impacted": 0.68,
  "commentary": 0.777,
  "folk": 1.514,
  "impressed": 0.285,
  "closeness": 3.453,
  "noughties": 3.533,
  "leader": 0.935,
  "maybe": 1.068,
  "advert": 2.903,
  "television": 0.285,
  "adverts": 2.906,
  "teenage": 1.09,
  "series": 0.935,
  "cartoon": 3.914,
  "characters": 2.587,
  "guys": 3.984,
  "man": 0.935,
  "kept": 0.935,
  "supermarket": 0.975,
  "guy": 1.415,
  "milk": 1.494,
  "politicians": 0.935,
  "focused": 0.68,
  "aged": 0.68,
  "calls": 0.68,
  "proponent": 3.914,
  "removing": 0.935,
  "counter": 0.68,
  "vividly": 1.95,
  "picking": 0.244,
  "stayed": 0.957,
  "night": 1.068,
  "roles": 0.68,
  "involve": 0.68,
  "shifts": 0.817,
  "counts": 0.879,
  "fan": 0.438,
  "breaking": 1.068,
  "illiterate": 2.401,
  "advocate": 1.15,
  "langley": 2.899,
  "academy": 0.68,
  "awareness": 0.935,
  "values": 0.935,
  "photo": 2.031,
  "overhead": 2.366,
  "insightful": 2.235,
  "remind": 0.68,
  "intervened": 0.667,
  "pupils": 1.068,
  "knowledge": 0.935,
  "pupil": 0.787,
  "cardiff": 0.438,
  "headteacher": 1.338,
  "robert": 0.327,
  "smyth": 3.177,
  "taught": 0.279,
  "class": 0.68,
  "disappointing": 0.935,
  "joining": 0.935,
  "impart": 4.668,
  "gained": 0.742,
  "experiences": 0.68,
  "chambers": 0.802,
  "educator": 4.032,
  "apprenticeships": 0.68,
  "engineering": 0.68,
  "apprenticeship": 0.41,
  "repeatedly": 0.68,
  "throughout": 0.68,
  "au": 4.032,
  "fait": 4.162,
  "receive": 0.68,
  "afternoon": 0.68,
  "tiers": 2.401,
  "mayors": 0.508,
  "mps": 0.68,
  "reorganising": 3.807,
  "father": 0.935,
  "arise": 0.68,
  "interesting": 0.68,
  "speakers": 0.68,
  "weird": 4.054,
  "hotchpotch": 7.328,
  "differences": 1.068,
  "simplified": 1.849,
  "standardised": 2.031,
  "refers": 0.68,
  "temporarily": 1.475,
  "fixed": 0.68,
  "causes": 1.15,
  "adequately": 0.68,
  "describing": 0.34,
  "complexities": 1.791,
  "addressing": 0.68,
  "hopeless": 2.267,
  "romantic": 3.378,
  "contrary": 0.935,
  "localised": 1.899,
  "bus": 1.205,
  "holder": 1.598,
  "reporting": 0.68,
  "veterans": 1.15,
  "omission": 1.265,
  "shameful": 0.68,
  "talked": 0.68,
  "cherry": 2.942,
  "varieties": 4.308,
  "european": 0.68,
  "mindful": 0.68,
  "method": 0.709,
  "filibustering": 4.474,
  "dismay": 1.925,
  "intended": 1.068,
  "peculiarity": 4.308,
  "unwittingly": 4.283,
  "worse": 0.68,
  "nonsensical": 2.366,
  "bureaucratic": 0.537,
  "heaped": 4.162,
  "nobody": 0.935,
  "accident": 0.935,
  "raft": 1.395,
  "remits": 3.453,
  "boundary": 0.787,
  "commissions": 2.267,
  "revisiting": 2.757,
  "governance": 1.068,
  "patchwork": 1.977,
  "quilt": 4.474,
  "aspect": 0.68,
  "daft": 2.712,
  "falling": 0.68,
  "cycle": 0.68,
  "trend": 0.68,
  "enthuse": 4.308,
  "bonds": 1.454,
  "tested": 0.68,
  "bizarre": 0.927,
  "assume": 0.935,
  "quick": 0.68,
  "inconvenient": 2.332,
  "rushed": 0.917,
  "whenever": 0.68,
  "presented": 0.68,
  "strengths": 0.712,
  "arranged": 1.577,
  "rarely": 0.313,
  "enables": 0.68,
  "safeguarding": 1.068,
  "holyrood": 1.04,
  "digitise": 3.533,
  "confuse": 2.95,
  "rely": 0.935,
  "disabilities": 0.935,
  "rental": 0.975,
  "contracts": 0.68,
  "uphold": 0.68,
  "flourishes": 3.914,
  "inclusive": 0.935,
  "citizen": 0.935,
  "oversaw": 1.357,
  "serving": 0.68,
  "contributing": 0.68,
  "wellbeing": 0.68,
  "safeguard": 0.68,
  "legitimacy": 2.541,
  "tier": 0.68,
  "broader": 0.935,
  "cornerstone": 0.494,
  "lies": 0.935,
  "participating": 0.638,
  "personal": 0.68,
  "tools": 0.68,
  "evolve": 1.357,
  "expectations": 0.68,
  "upheld": 0.602,
  "update": 0.68,
  "respecting": 0.942,
  "uniformly": 3.807,
  "timely": 0.68,
  "hold": 0.68,
  "belief": 0.68,
  "demonstrate": 0.68,
  "originally": 0.68,
  "declined": 0.313,
  "motions": 0.802,
  "submit": 0.566,
  "modify": 2.587,
  "reforms": 1.068,
  "enabling": 0.935,
  "diverge": 2.85,
  "legislatures": 2.401,
  "aligning": 1.777,
  "practicable": 1.454,
  "confuses": 4.162,
  "ultimate": 0.027,
  "historically": 0.081,
  "lagged": 3.618,
  "evidenced": 1.107,
  "compared": 0.68,
  "comparatively": 2.548,
  "fraud": 0.68,
  "toughen": 2.803,
  "strict": 0.299,
  "verification": 1.619,
  "checks": 1.068,
  "copy": 0.68,
  "fraudsters": 2.087,
  "divert": 1.535,
  "malpractice": 2.899,
  "venue": 1.007,
  "lax": 3.378,
  "electronic": 0.466,
  "external": 0.68,
  "interference": 0.34,
  "hostile": 0.244,
  "actor": 1.777,
  "literally": 0.68,
  "anywhere": 0.68,
  "operational": 0.68,
  "consulting": 0.68,
  "indicate": 0.19,
  "interacts": 2.67,
  "opt": 0.817,
  "worth": 0.68,
  "noting": 0.244,
  "highlights": 0.935,
  "preparation": 0.679,
  "legal": 1.068,
  "resolved": 0.68,
  "euan": 3.453,
  "adam": 1.124,
  "thompson": 2.003,
  "southport": 1.874,
  "patrick": 1.663,
  "hurley": 4.162,
  "brentford": 4.366,
  "isleworth": 4.745,
  "ruth": 2.109,
  "cadbury": 3.788,
  "bathgate": 3.004,
  "linlithgow": 2.332,
  "kirsteen": 4.032,
  "sullivan": 2.548,
  "tonia": 3.453,
  "antoniazzi": 3.378,
  "claire": 0.927,
  "hughes": 1.395,
  "martin": 0.935,
  "rhodes": 5.096,
  "patricia": 3.449,
  "ferguson": 3.072,
  "rushcliffe": 2.95,
  "james": 0.68,
  "naish": 3.308,
  "individuals": 0.68,
  "younger": 0.68,
  "highlighted": 0.68,
  "widening": 1.193,
  "legitimate": 0.68,
  "encouraged": 0.68,
  "franchise": 1.708,
  "appropriately": 0.68,
  "puts": 0.68,
  "articulated": 1.357,
  "repeat": 0.68,
  "overview": 2.401,
  "print": 1.825,
  "cumbersome": 2.899,
  "allocation": 0.68,
  "reality": 0.68,
  "facilitating": 0.537,
  "assure": 0.935,
  "acknowledge": 0.935,
  "findings": 0.935,
  "minority": 0.68,
  "packs": 2.803,
  "overseas": 0.68,
  "remained": 0.68,
  "designing": 1.09,
  "adoption": 0.802,
  "incurred": 0.817,
  "fed": 0.68,
  "twice": 0.68,
  "plagues": 4.032,
  "nights": 1.415,
  "luton": 1.307,
  "sponsors": 2.003,
  "peterborough": 0.975,
  "pakes": 3.241,
  "newport": 1.535,
  "jessica": 1.849,
  "morden": 1.95,
  "affect": 1.068,
  "pets": 3.253,
  "elderly": 0.68,
  "spoke": 0.68,
  "detrimental": 0.167,
  "reported": 1.068,
  "worst": 0.68,
  "antisocial": 0.68,
  "weapon": 0.537,
  "laws": 0.68,
  "rock": 1.158,
  "concert": 1.454,
  "bite": 2.166,
  "suffering": 0.68,
  "parents": 0.68,
  "distressing": 0.449,
  "middle": 0.68,
  "non": 0.68,
  "verbal": 1.777,
  "calming": 3.177,
  "loved": 0.68,
  "sporadic": 4.032,
  "distress": 0.935,
  "barrage": 2.51,
  "uncontrolled": 2.332,
  "veterinary": 1.357,
  "surgeon": 1.708,
  "animals": 0.843,
  "cowering": 3.618,
  "animal": 0.242,
  "livestock": 1.494,
  "horses": 1.494,
  "bolt": 3.618,
  "injuries": 0.122,
  "extensive": 0.68,
  "vet": 2.712,
  "iterations": 2.587,
  "kennel": 5.54,
  "club": 0.935,
  "dogs": 1.544,
  "behaviour": 0.68,
  "trained": 0.68,
  "guide": 0.449,
  "dog": 0.621,
  "users": 0.68,
  "alluded": 0.354,
  "represents": 0.68,
  "bone": 1.265,
  "sales": 0.68,
  "emails": 0.258,
  "traumatised": 1.415,
  "woken": 2.757,
  "ptsd": 3.117,
  "combat": 0.68,
  "heroes": 0.551,
  "rspca": 4.162,
  "charities": 0.68,
  "loudest": 2.85,
  "eventually": 0.68,
  "credit": 0.68,
  "injured": 0.68,
  "killed": 0.68,
  "letterbox": 3.709,
  "senior": 0.68,
  "import": 0.041,
  "sale": 0.68,
  "proactive": 0.68,
  "reacting": 2.757,
  "explosives": 4.283,
  "criminal": 0.68,
  "ends": 0.68,
  "horrendous": 0.122,
  "perverse": 1.107,
  "loophole": 0.354,
  "unlicensed": 3.851,
  "sellers": 3.916,
  "diwali": 2.628,
  "eve": 2.115,
  "pop": 1.141,
  "shops": 0.68,
  "appear": 0.68,
  "handled": 0.682,
  "lowest": 0.68,
  "safest": 2.205,
  "hayley": 3.308,
  "adel": 4.9,
  "kilter": 3.117,
  "devastating": 0.68,
  "wildlife": 0.864,
  "tragic": 0.68,
  "zoo": 2.95,
  "manage": 0.68,
  "decibel": 4.9,
  "motion": 1.405,
  "object": 1.253,
  "roughton": 11.767,
  "surrounding": 0.68,
  "furious": 1.708,
  "prospect": 0.68,
  "lifeline": 0.506,
  "banking": 0.108,
  "petition": 1.15,
  "collective": 0.68,
  "petitioners": 0.275,
  "commons": 0.935,
  "urges": 1.317,
  "existence": 0.935,
  "etc": 0.935,
  "text": 0.68,
  "declares": 0.217,
  "gen": 2.299,
  "kitchen": 0.817,
  "secured": 0.68,
  "entering": 0.68,
  "origins": 1.925,
  "century": 0.68,
  "elizabeth": 0.452,
  "impose": 0.935,
  "miles": 0.68,
  "spread": 0.68,
  "plague": 2.205,
  "counties": 1.555,
  "undeveloped": 4.162,
  "hectares": 2.332,
  "heading": 0.258,
  "essex": 1.299,
  "securing": 0.68,
  "precious": 0.935,
  "reclassify": 4.308,
  "shying": 3.618,
  "densification": 7.328,
  "cities": 1.205,
  "failed": 0.68,
  "failure": 1.068,
  "redevelop": 2.85,
  "edges": 1.395,
  "designated": 1.068,
  "insidious": 1.95,
  "phrasing": 4.032,
  "dense": 3.914,
  "paris": 0.958,
  "mad": 1.454,
  "virgin": 1.619,
  "subsidise": 1.874,
  "density": 2.205,
  "routes": 0.935,
  "links": 0.68,
  "spilled": 3.378,
  "knighthood": 3.533,
  "destruction": 1.15,
  "emergence": 2.473,
  "contiguous": 6.148,
  "conurbation": 6.533,
  "shoeburyness": 5.19,
  "thames": 0.027,
  "gateway": 0.958,
  "corridor": 0.508,
  "brentwood": 3.914,
  "uxbridge": 1.685,
  "essentially": 0.68,
  "heathrow": 1.357,
  "airport": 0.019,
  "southend": 0.958,
  "parish": 0.623,
  "overwhelmingly": 0.523,
  "argument": 0.68,
  "erosion": 0.757,
  "fourthly": 0.638,
  "gun": 1.708,
  "se": 3.059,
  "entrepreneurial": 2.235,
  "oriented": 3.914,
  "whack": 3.177,
  "dwellings": 2.366,
  "shy": 0.58,
  "vandalism": 1.514,
  "merging": 3.881,
  "wickford": 4.715,
  "continuous": 0.494,
  "bearing": 0.68,
  "justified": 0.667,
  "concentrating": 2.332,
  "wood": 0.48,
  "spaces": 0.935,
  "accepted": 0.68,
  "modifications": 2.299,
  "mass": 0.68,
  "hill": 1.068,
  "noak": 7.692,
  "bridge": 0.935,
  "footnotes": 4.162,
  "oversubscribed": 2.299,
  "acute": 1.068,
  "healthcare": 0.68,
  "tens": 0.68,
  "classic": 1.158,
  "stretched": 0.327,
  "arterial": 3.618,
  "massively": 0.68,
  "stake": 0.935,
  "programmes": 0.68,
  "nowhere": 0.68,
  "churning": 3.914,
  "unitary": 1.663,
  "pushed": 0.68,
  "irreversible": 1.474,
  "outraged": 1.685,
  "congratulating": 0.68,
  "redevelopment": 1.376,
  "clarify": 0.68,
  "unless": 0.68,
  "substantial": 0.68,
  "informing": 1.211,
  "passport": 0.864,
  "september": 0.68,
  "urban": 0.68,
  "volume": 0.041,
  "viable": 0.68,
  "attach": 2.205,
  "belts": 4.745,
  "unrestricted": 2.436,
  "sprawl": 2.899,
  "preventing": 0.68,
  "paragraph": 0.68,
  "propose": 0.68,
  "designation": 2.025,
  "release": 0.68,
  "released": 0.935,
  "haphazard": 3.177,
  "speculative": 2.828,
  "sequential": 4.032,
  "releasing": 0.991,
  "performing": 0.111,
  "identify": 0.68,
  "definition": 0.935,
  "aesthetic": 3.618,
  "funding": 0.935,
  "totalling": 1.514,
  "reviews": 0.68,
  "identifying": 0.68,
  "swathes": 1.357,
  "ensured": 0.935,
  "hospital": 1.205,
  "bed": 0.935,
  "flu": 2.299,
  "exceeded": 1.619,
  "patients": 0.935,
  "bursting": 2.332,
  "seams": 2.899,
  "unsound": 3.807,
  "score": 1.283,
  "relation": 0.68,
  "statements": 0.68,
  "document": 0.68,
  "theory": 0.911,
  "quasi": 2.442,
  "judicial": 0.935,
  "specifics": 0.373,
  "premium": 0.48,
  "assessments": 0.68,
  "permitting": 2.087,
  "disconnected": 2.174,
  "sustainably": 1.494,
  "located": 0.217,
  "versatile": 2.628,
  "preserved": 1.849,
  "safeguarded": 1.641,
  "recovery": 0.68,
  "assessing": 0.149,
  "partly": 0.68,
  "responsiveness": 3.308,
  "affordability": 0.991,
  "rayleigh": 4.127,
  "underline": 0.697,
  "depend": 0.68,
  "moving": 0.68,
  "universal": 0.935,
  "sub": 0.68,
  "regions": 0.68,
  "strategies": 0.244,
  "attempting": 0.244,
  "confines": 2.85,
  "inherited": 0.68,
  "frankly": 0.68,
  "appalling": 0.68,
  "expectation": 0.68,
  "affairs": 0.68,
  "unplanned": 2.95,
  "experiencing": 0.68,
  "compulsory": 0.566,
  "reinforces": 1.731,
  "acted": 0.68,
  "failures": 0.68,
  "predecessors": 0.935,
  "emerges": 2.436,
  "sad": 0.68,
  "reflection": 0.081,
  "intervene": 0.68,
  "timetable": 0.68,
  "explore": 0.68,
  "maximising": 1.494,
  "reviewing": 0.68
}